{
    "4": [
        "VASE",
        "EASE",
        "ASEA",
        "RASE",
        "LASE",
        "CASE",
        "PASE",
        "WASE",
        "MASE",
        "BASE"
    ],
    "5": [
        "CASED",
        "GASES",
        "LEASE",
        "MASER",
        "EASED",
        "SEASE",
        "CHASE",
        "MASES",
        "ABASE",
        "PHASE",
        "LYASE",
        "URASE",
        "TEASE",
        "BLASE",
        "WASES",
        "CASES",
        "LASER",
        "PASES",
        "TASER",
        "LASED",
        "ERASE",
        "PEASE",
        "BASES",
        "BASED",
        "PASEO",
        "PRASE",
        "JASEY",
        "RASER",
        "UKASE",
        "OASES",
        "MASED",
        "BASER",
        "SASER",
        "CEASE",
        "EASEL",
        "VASES",
        "LASES",
        "RASED",
        "RASES",
        "FEASE",
        "EASES",
        "EASER",
        "MEASE"
    ],
    "6": [
        "EASELS",
        "ZYMASE",
        "PEASED",
        "NYASES",
        "MASERS",
        "CHASER",
        "CREASE",
        "INCASE",
        "UPASES",
        "PASEOS",
        "UNEASE",
        "ERASED",
        "SASERS",
        "ABASES",
        "PREASE",
        "CHASED",
        "CASEIN",
        "DEBASE",
        "IMBASE",
        "SEASED",
        "BIASED",
        "TEASED",
        "LEASES",
        "FEASED",
        "LYASES",
        "MEASED",
        "EASERS",
        "GREASE",
        "JASEYS",
        "TEASES",
        "PASELA",
        "BAASES",
        "PRASES",
        "ABASER",
        "KINASE",
        "CASEFY",
        "ERASER",
        "URASES",
        "CASERN",
        "PHASED",
        "PEASEN",
        "CHASES",
        "LIGASE",
        "CEASED",
        "GYRASE",
        "UTASES",
        "BIASES",
        "CYTASE",
        "TEASEL",
        "CASEIC",
        "PHRASE",
        "MYASES",
        "RASERS",
        "KVASES",
        "LEASER",
        "PASEAR",
        "MEASES",
        "LEASED",
        "STASES",
        "UNCASE",
        "LIASES",
        "PLEASE",
        "PHASES",
        "LASERS",
        "SEASES",
        "ABASED",
        "BASEST",
        "MUTASE",
        "LIPASE",
        "UREASE",
        "UKASES",
        "CRASES",
        "CEASES",
        "PEASES",
        "TASERS",
        "EMBASE",
        "ERASES",
        "TEASER",
        "FLASER",
        "WEASEL",
        "MAASES",
        "ASEITY",
        "EYASES",
        "ENCASE",
        "BASELY",
        "BRASES",
        "FEASES"
    ],
    "7": [
        "GASEOUS",
        "CASERNE",
        "ATLASES",
        "ASEPTIC",
        "RELEASE",
        "CARCASE",
        "GASEITY",
        "CREASES",
        "BASEMEN",
        "AIRBASE",
        "ZYMASES",
        "PASEARS",
        "ASEPSES",
        "TEXASES",
        "INCASES",
        "LIPASES",
        "RUDASES",
        "DEBASES",
        "UREASES",
        "ENOLASE",
        "NARASES",
        "PALASES",
        "HYDRASE",
        "NUTCASE",
        "ERASERS",
        "FLASERS",
        "DECEASE",
        "EASELED",
        "DIAPASE",
        "MUTASES",
        "ASEXUAL",
        "PLEASES",
        "PERCASE",
        "ARRASED",
        "CYTASES",
        "OXIDASE",
        "CYCASES",
        "UNEASES",
        "MALTASE",
        "PSOASES",
        "CASEASE",
        "CASEATE",
        "LACTASE",
        "JUDASES",
        "ENCASES",
        "PLEASED",
        "ENCHASE",
        "BOLASES",
        "ALIASES",
        "CYCLASE",
        "EMBASES",
        "PINCASE",
        "TEASERS",
        "CREASER",
        "LIGASES",
        "DIABASE",
        "PHRASER",
        "BALASES",
        "SUBBASE",
        "CHASERS",
        "MISEASE",
        "BASENJI",
        "INULASE",
        "DISEASE",
        "PLAASES",
        "UNCASED",
        "BRASERO",
        "SURBASE",
        "AVGASES",
        "ANATASE",
        "CASERNS",
        "CASETTE",
        "SUCRASE",
        "PHRASED",
        "PREASED",
        "DISCASE",
        "INCHASE",
        "ENTASES",
        "MYIASES",
        "ECTASES",
        "APYRASE",
        "URICASE",
        "DEBASER",
        "PHASEAL",
        "DEGASES",
        "CASEOSE",
        "DIPHASE",
        "CREASED",
        "WEASELS",
        "ASEPSIS",
        "APPEASE",
        "ANLASES",
        "PECTASE",
        "KINASES",
        "ARRASES",
        "INCASED",
        "CASEOUS",
        "WEASELY",
        "GYRASES",
        "TEASELS",
        "AMIDASE",
        "GREASER",
        "FANBASE",
        "IMBASES",
        "INPHASE",
        "GREASED",
        "TASERED",
        "CASEINS",
        "LEASERS",
        "EMBASED",
        "CASEMAN",
        "PREASES",
        "GREASES",
        "GUANASE",
        "CAMASES",
        "PASELAS",
        "ABASERS",
        "ENCASED",
        "RENNASE",
        "UNCASES",
        "ISOBASE",
        "PLEASER",
        "EUCLASE",
        "DEBASED",
        "AMYLASE",
        "PHRASES",
        "IMBASED",
        "MONASES",
        "BASEMAN",
        "EASEFUL",
        "UNBASED",
        "CASEMEN"
    ],
    "8": [
        "SUITCASE",
        "NOTECASE",
        "SURBASES",
        "CASEFIES",
        "BIOGASES",
        "CASERNES",
        "DIABASES",
        "SHOWCASE",
        "BASELARD",
        "RELEASEE",
        "AMIDASES",
        "ASEISMIC",
        "RENNASES",
        "ANATASES",
        "CREASERS",
        "ANAPHASE",
        "UNBIASES",
        "ISOBASES",
        "HYDRASES",
        "POSTBASE",
        "CASEOSES",
        "DATABASE",
        "LAMASERY",
        "PECTASES",
        "SIRIASES",
        "ESTERASE",
        "KILOBASE",
        "VASELIKE",
        "SURCEASE",
        "CASEWORK",
        "BRASEROS",
        "CAPIASES",
        "DISCASES",
        "KILLASES",
        "CANVASER",
        "RELEASER",
        "SUBLEASE",
        "SYNGASES",
        "PORTASES",
        "FRACASES",
        "UNBIASED",
        "MADRASES",
        "SUBBASES",
        "GEARCASE",
        "PURCHASE",
        "ASEITIES",
        "ENOLASES",
        "WEASELED",
        "CASETTES",
        "PHRASERS",
        "APPEASER",
        "CHARASES",
        "EASEMENT",
        "CASEFIED",
        "ANANASES",
        "ENCHASES",
        "CASEBOOK",
        "INCREASE",
        "CARDCASE",
        "DISCASED",
        "PLEASETH",
        "BASEBAND",
        "ENCHASED",
        "PERMEASE",
        "PROTEASE",
        "LAMPASES",
        "ARRASENE",
        "BASEBORN",
        "EPITASES",
        "CANVASES",
        "UNLEASED",
        "WEASELLY",
        "NUTCASES",
        "PAMPASES",
        "CARCASES",
        "CASEMATE",
        "BASENJIS",
        "CASEATES",
        "TEASELED",
        "BASEBALL",
        "MISEASES",
        "CASELOAD",
        "FANBASES",
        "ARGINASE",
        "TARRASES",
        "ECSTASES",
        "CASEWORM",
        "ECRASEUR",
        "SUBPHASE",
        "BASELINE",
        "ANABASES",
        "APYRASES",
        "RHEOBASE",
        "URICASES",
        "GASELIER",
        "DECEASES",
        "DISEASES",
        "OXIDASES",
        "MALTASES",
        "DIASTASE",
        "SURBASED",
        "ABASEDLY",
        "PLEASERS",
        "OILGASES",
        "DECEASED",
        "BASENESS",
        "DEGREASE",
        "GUANASES",
        "TASERING",
        "NARRASES",
        "TERRASES",
        "DEBASERS",
        "CATALASE",
        "BOREASES",
        "OUBAASES",
        "PHASEOUT",
        "CANVASED",
        "APPEASES",
        "CUTLASES",
        "LONGCASE",
        "OUTGASES",
        "EASELESS",
        "SEEDCASE",
        "ASEPTATE",
        "INULASES",
        "CASEATED",
        "GOLIASED",
        "NUCLEASE",
        "TEASELER",
        "PEASECOD",
        "BOOKCASE",
        "INCHASES",
        "ENCHASER",
        "PINCASES",
        "ELASTASE",
        "HARDCASE",
        "TIZWASES",
        "DIAPASES",
        "DOORCASE",
        "ALDOLASE",
        "ASEPTICS",
        "GOLIASES",
        "ENCREASE",
        "UNERASED",
        "DIOPTASE",
        "REPHRASE",
        "WINDASES",
        "AMYLASES",
        "WEASELER",
        "APPEASED",
        "CARCASED",
        "SLIPCASE",
        "AIRBASES",
        "VASELINE",
        "DISEASED",
        "CASEMENT",
        "RELEASES",
        "TISWASES",
        "EMPHASES",
        "PROTASES",
        "INCHASED",
        "CASEASES",
        "CYCLASES",
        "TYPECASE",
        "FREEBASE",
        "GREASERS",
        "PROPHASE",
        "TENIASES",
        "IDOCRASE",
        "PASEARED",
        "HEADCASE",
        "EUCLASES",
        "LACTASES",
        "RELEASED",
        "DOWLASES",
        "DECREASE",
        "BIASEDLY",
        "BASELESS",
        "FUMARASE",
        "TRIPHASE",
        "SUCRASES",
        "BASEMENT",
        "FIREBASE"
    ],
    "9": [
        "NUCLEASES",
        "EKPHRASES",
        "DISPLEASE",
        "BASEBALLS",
        "PERICLASE",
        "APPEASERS",
        "BASELARDS",
        "CZARDASES",
        "SUBLEASES",
        "KILOBASES",
        "REPHRASES",
        "MISBIASES",
        "UNPLEASED",
        "CASEINATE",
        "ARRASENES",
        "MONOPHASE",
        "FIREBASES",
        "ANAPHASES",
        "RELEASERS",
        "OXYGENASE",
        "UPPERCASE",
        "TAENIASES",
        "PASEARING",
        "BOOKCASES",
        "PHASELESS",
        "EASEMENTS",
        "MOONPHASE",
        "CASEBOOKS",
        "NOTECASES",
        "LOWERCASE",
        "UROKINASE",
        "DOORCASES",
        "ACARIASES",
        "CEASEFIRE",
        "STAIRCASE",
        "CASELOADS",
        "BASEMENTS",
        "ARGINASES",
        "EPIMERASE",
        "DATABASED",
        "DEGREASES",
        "INVERTASE",
        "CASEWORKS",
        "VERGLASES",
        "SHOWCASES",
        "METABASES",
        "PHASEOLIN",
        "PHRASEMAN",
        "CEASELESS",
        "FREEBASES",
        "ISOMERASE",
        "PHASEDOWN",
        "KATABASES",
        "PLEASEDLY",
        "APSARASES",
        "SUBLEASED",
        "DECREASES",
        "POLYPHASE",
        "BRAATASES",
        "KOPASETIC",
        "ECRASEURS",
        "PHASEOUTS",
        "TEARGASES",
        "SUBCHASER",
        "CASEATION",
        "VANITASES",
        "CHASEPORT",
        "RAKSHASES",
        "PROTEASES",
        "LAMASERAI",
        "ALDOLASES",
        "IDOCRASES",
        "CELLULASE",
        "CASEMATES",
        "EASEFULLY",
        "REDUCTASE",
        "APOPHASES",
        "AMEBIASES",
        "PSORIASES",
        "PURCHASED",
        "CASEMENTS",
        "MISBIASED",
        "RERELEASE",
        "ASEPALOUS",
        "RHEOBASES",
        "PLEASEMEN",
        "COAGULASE",
        "WEASELLED",
        "SURCEASED",
        "HEADLEASE",
        "KLIPDASES",
        "PLEASEMAN",
        "VASELINES",
        "SMIERCASE",
        "CASEATING",
        "REPLICASE",
        "CASEBOUND",
        "SUBPHASES",
        "PURCHASES",
        "WEASELLER",
        "BASELINER",
        "LEASEHOLD",
        "SHOWCASED",
        "WATCHCASE",
        "IXODIASES",
        "WEASELING",
        "UNDEBASED",
        "CASEWORMS",
        "HYDROLASE",
        "PRECREASE",
        "SLIPCASED",
        "ENCREASED",
        "BASEBOARD",
        "FREEBASER",
        "EPISTASES",
        "INCREASES",
        "BASEPLATE",
        "CASEMAKER",
        "WEASELERS",
        "TEASELING",
        "AROMATASE",
        "METAPHASE",
        "PEASECODS",
        "ANHYDRASE",
        "CARITASES",
        "TYPECASES",
        "TEASELLED",
        "FUMARASES",
        "SULFATASE",
        "ELASTASES",
        "BRIEFCASE",
        "DATABASES",
        "PARABASES",
        "ENCREASES",
        "ATTOLASER",
        "DEGREASER",
        "GASELIERS",
        "COPASETIC",
        "ABRAXASES",
        "PURCHASER",
        "LASERDISC",
        "ASEXUALLY",
        "CARDCASES",
        "DIOPTASES",
        "LEASEBACK",
        "SMEARCASE",
        "TEASELERS",
        "INCREASED",
        "BASEBANDS",
        "UNGREASED",
        "HEADCASES",
        "ERASEMENT",
        "NASEBERRY",
        "LITHIASES",
        "SEEDCASES",
        "REPHRASED",
        "PROPHASES",
        "WHEREASES",
        "LASERDISK",
        "SURCEASES",
        "ENCHASERS",
        "MISPHRASE",
        "METHYLASE",
        "LASERWORT",
        "CANVASERS",
        "FREEBASED",
        "MYDRIASES",
        "CHASEABLE",
        "WHEELBASE",
        "TEASELLER",
        "CASEFYING",
        "INCREASER",
        "CATALASES",
        "MISPLEASE",
        "PERMEASES",
        "PEPTIDASE",
        "DIASTASES",
        "ABASEMENT",
        "ESTERASES",
        "DEGREASED",
        "CSARDASES",
        "CRANKCASE",
        "GASEITIES",
        "GEARCASES",
        "CATABASES",
        "BASELINES",
        "SUITCASES",
        "VASECTOMY",
        "SLIPCASES",
        "DEAMINASE",
        "ANASTASES",
        "CASEMATED",
        "DECREASED",
        "MESSIASES",
        "TELOPHASE",
        "RELEASEES",
        "SYNAPTASE",
        "BRAINCASE",
        "PHRASEMEN"
    ],
    "10": [
        "ALCATRASES",
        "BABESIASES",
        "GREASEWOOD",
        "DEXTRANASE",
        "BASENESSES",
        "PERICLASES",
        "MOONPHASES",
        "HEXOKINASE",
        "CASEMENTED",
        "DIAPHORASE",
        "REPURCHASE",
        "INCREASERS",
        "CRANKCASES",
        "COPPERASES",
        "HEARTSEASE",
        "BUCELLASES",
        "CASEBEARER",
        "UNBIASEDLY",
        "PREDECEASE",
        "DEBASEMENT",
        "PURCHASERS",
        "SULFATASES",
        "OXYGENASES",
        "HYDROLASES",
        "THIAMINASE",
        "PEPTIDASES",
        "CASEINATES",
        "ENCASEMENT",
        "SACCHARASE",
        "CREASELESS",
        "INCASEMENT",
        "PILLOWCASE",
        "GREASELESS",
        "METAPLASES",
        "MISPLEASES",
        "LEASEHOLDS",
        "HEADLEASES",
        "METASTASES",
        "TARANTASES",
        "BASELESSLY",
        "STRIPTEASE",
        "ATTOLASERS",
        "PHASEDOWNS",
        "CORPORASES",
        "LEASEBACKS",
        "LASERWORTS",
        "SUBCHASERS",
        "CERVELASES",
        "PROTEINASE",
        "BASEBOARDS",
        "BASEPLATES",
        "HYPOSTASES",
        "RERELEASES",
        "LAMASERIES",
        "ISOMERASES",
        "UROKINASES",
        "TEASELLERS",
        "SYNAPTASES",
        "LEONTIASES",
        "UPPERCASES",
        "COAGULASES",
        "EMBASEMENT",
        "SATYRIASES",
        "TEASELLING",
        "TEASELINGS",
        "ASCARIASES",
        "GREASEBUSH",
        "CEASEFIRES",
        "TELOPHASES",
        "INVERTASES",
        "MULTIPHASE",
        "TRICHIASES",
        "CASEWORKER",
        "MESHUGASEN",
        "DISPLEASES",
        "ASEPTICISM",
        "ASEPTICIZE",
        "ASEPTICISE",
        "TASEOMETER",
        "ASEXUALITY",
        "PANCREASES",
        "SALMANASER",
        "EPIMERASES",
        "GRAVITASES",
        "METAPHRASE",
        "DISPLEASED",
        "BONAMIASES",
        "REPLICASES",
        "PEROXIDASE",
        "GIARDIASES",
        "DEAMINASES",
        "TETRASEMIC",
        "GREASEBALL",
        "WHEELBASES",
        "LOWERCASED",
        "FILARIASES",
        "PARASELENE",
        "GREASEBAND",
        "AROMATASES",
        "ANHYDRASES",
        "UNDERLEASE",
        "BASERUNNER",
        "BRAINCASES",
        "DISEASEFUL",
        "STAIRCASED",
        "PARASEXUAL",
        "CASEATIONS",
        "WATCHCASES",
        "HOLOPHRASE",
        "MISPLEASED",
        "LUCIFERASE",
        "ABASEMENTS",
        "CASEINOGEN",
        "FREEBASERS",
        "STAIRCASES",
        "INTERPHASE",
        "PRECREASED",
        "REINCREASE",
        "ORTHOCLASE",
        "MISPHRASES",
        "WEASELLING",
        "RERELEASED",
        "CHASEPORTS",
        "REDUCTASES",
        "BASEBURNER",
        "PERIPHRASE",
        "SCLERIASES",
        "UPPERCASED",
        "METHYLASES",
        "OLIGOCLASE",
        "CELLULASES",
        "BASELINERS",
        "PHASEOLINS",
        "PARACASEIN",
        "SMIERCASES",
        "PARAPHRASE",
        "POLYMERASE",
        "CASEMAKERS",
        "PHOTOPHASE",
        "MISPHRASED",
        "PITYRIASES",
        "LOWERCASES",
        "TYROSINASE",
        "INSULINASE",
        "COCKTEASER",
        "DIPLOPHASE",
        "LASERDISCS",
        "PRECREASES",
        "SULPHATASE",
        "WEASELLERS",
        "SMEARCASES",
        "PHRASELESS",
        "HEMOSTASES",
        "LASERDISKS",
        "MONILIASES",
        "SPRINGHASE",
        "REEMPHASES",
        "BASEBALLER",
        "CATASTASES",
        "UNAPPEASED",
        "AMOEBIASES",
        "SYNTHETASE",
        "TELOMERASE",
        "BRIEFCASES",
        "TAFFETASES",
        "NONGASEOUS",
        "PRERELEASE",
        "LAMASERAIS",
        "CATACLASES",
        "ERASEMENTS",
        "DEGREASERS",
        "OXYURIASES",
        "METAPHASES"
    ],
    "11": [
        "GREASEWOODS",
        "BASEBURNERS",
        "GREASEBANDS",
        "APPEASEMENT",
        "ENCASEMENTS",
        "GLYCOSIDASE",
        "UNDERLEASES",
        "RELEASEMENT",
        "CHRYSOPRASE",
        "BROUGHTASES",
        "DINOCERASES",
        "ASCLEPIASES",
        "HEXOKINASES",
        "UNPURCHASED",
        "TIMEPLEASER",
        "LEASEHOLDER",
        "GLUCOKINASE",
        "PARAPHRASES",
        "GLUTAMINASE",
        "PARAPHRASED",
        "PLAGIOCLASE",
        "CATCHPHRASE",
        "NASEBERRIES",
        "MISHEGAASEN",
        "HAMADRYASES",
        "REINCREASED",
        "THIAMINASES",
        "SYNTHETASES",
        "INSULINASES",
        "METASEQUOIA",
        "SUBBASEMENT",
        "NITROGENASE",
        "PHRASEOGRAM",
        "EASEFULNESS",
        "SULPHATASES",
        "PREPURCHASE",
        "HIPPOCRASES",
        "BASERUNNERS",
        "PEROXIDASES",
        "HYDROXYLASE",
        "PROTEINASES",
        "INCREASEFUL",
        "ULTRASECRET",
        "PLUMDAMASES",
        "CASEBEARERS",
        "PHRASEMAKER",
        "INCASEMENTS",
        "ASEPTICISED",
        "OLIGOCLASES",
        "GLUCOSIDASE",
        "TRANSFERASE",
        "PILLOWCASES",
        "HOMEOSTASES",
        "HYDROGENASE",
        "BRAINTEASER",
        "COLLAGENASE",
        "STEENBRASES",
        "PRERELEASED",
        "METAPHRASES",
        "HISTAMINASE",
        "TYROSINASES",
        "OSTEOCLASES",
        "SALMANASERS",
        "TEASELLINGS",
        "ORTHOCLASES",
        "ASEPTICALLY",
        "GREASEPROOF",
        "ICONOSTASES",
        "HEARTSEASES",
        "HOLOPHRASES",
        "ASEPTICIZES",
        "INCREASEDLY",
        "STRIPTEASER",
        "REPURCHASES",
        "CASEWORKERS",
        "PARACASEINS",
        "ANTIPHRASES",
        "PHOTOPHASES",
        "GREASEBALLS",
        "REINCREASES",
        "SACCHARASES",
        "PREDECEASES",
        "POLYMERASES",
        "TELOMERASES",
        "HAEMOSTASES",
        "DIAPHORASES",
        "DEBASEDNESS",
        "SURBASEMENT",
        "PERIPHRASES",
        "DEXTRANASES",
        "REPURCHASED",
        "COCKTEASERS",
        "CHOLESTASES",
        "UNDERLEASED",
        "GASEOUSNESS",
        "PHTHIRIASES",
        "COUNTERBASE",
        "CEASELESSLY",
        "CANDIDIASES",
        "LUCIFERASES",
        "PERIPHRASED",
        "MESHUGAASEN",
        "VASECTOMIES",
        "CASEINOGENS",
        "VASECTOMISE",
        "PRERELEASES",
        "PSYCHOGASES",
        "MISEMPHASES",
        "VASECTOMIZE",
        "PHRASEOLOGY",
        "PARAPHRASER",
        "TASEOMETERS",
        "DIPEPTIDASE",
        "EMBASEMENTS",
        "ATELECTASES",
        "INTRASEXUAL",
        "PHOSPHATASE",
        "CARBOXYLASE",
        "STRIPTEASES",
        "LECITHINASE",
        "DEBASEMENTS",
        "ASEPTICISES",
        "PARASELENAE",
        "EXONUCLEASE",
        "BASERUNNING",
        "METAPHRASED",
        "INTERPHASES",
        "SASSAFRASES",
        "PREDECEASED",
        "BASEBALLERS",
        "DIPLOPHASES",
        "GREASEPAINT",
        "ASEPTICIZED",
        "ASEPTICISMS",
        "PARASELENIC"
    ],
    "12": [
        "TRANSFERASES",
        "OVEREMPHASES",
        "ASEPTICISING",
        "EXOPEPTIDASE",
        "PARAPHRASERS",
        "BASEMENTLESS",
        "HASENPFEFFER",
        "VASECTOMIZED",
        "ASEXUALITIES",
        "GLUCOKINASES",
        "GLUCOSIDASES",
        "UNBIASEDNESS",
        "VASECTOMISED",
        "FASCIOLIASES",
        "CARBOHYDRASE",
        "RIBONUCLEASE",
        "GALIMATIASES",
        "HISTAMINASES",
        "PHOSPHATASES",
        "RELEASEMENTS",
        "UNCINARIASES",
        "CHILDERMASES",
        "DRACONTIASES",
        "ASPARAGINASE",
        "BASELESSNESS",
        "TRICHINIASES",
        "APPEASEMENTS",
        "TOXOCARIASES",
        "TROMBIDIASES",
        "NUCLEOTIDASE",
        "COLLAGENASES",
        "STEEPLECHASE",
        "PHRASEOGRAMS",
        "LEASEHOLDERS",
        "DISTRINGASES",
        "UROLITHIASES",
        "PHRASEMAKERS",
        "ENTEROBIASES",
        "PHRASEMONGER",
        "SUBBASEMENTS",
        "METASEQUOIAS",
        "BILHARZIASES",
        "SURBASEMENTS",
        "HYDROGENASES",
        "CHRYSOPRASES",
        "STRIPTEASERS",
        "PHRASEOGRAPH",
        "PREPURCHASES",
        "BRAINTEASERS",
        "PHRASEMAKING",
        "HYDROXYLASES",
        "ERYSIPELASES",
        "VASECTOMIZES",
        "ULTRASENSUAL",
        "PREPURCHASED",
        "EXTRASENSORY",
        "GREASEBUSHES",
        "PLAGIOCLASES",
        "HOMOEOSTASES",
        "DIPEPTIDASES",
        "ULTRASERIOUS",
        "LECITHINASES",
        "ENTEROKINASE",
        "CATCHPHRASES",
        "NITROGENASES",
        "PRASEODYMIUM",
        "VASECTOMISES",
        "ENDONUCLEASE",
        "GLYCOSIDASES",
        "TRANSAMINASE",
        "TIMEPLEASERS",
        "CARBOXYLASES",
        "PHRASEOLOGIC",
        "GLUTAMINASES",
        "COUNTERBASES",
        "GREASEPROOFS",
        "EXONUCLEASES",
        "GREASEPAINTS",
        "DISPLEASEDLY",
        "TRICHURIASES",
        "DISEASEDNESS",
        "CONTRASEXUAL",
        "BASERUNNINGS",
        "ASEPTICIZING"
    ],
    "13": [
        "GLUCURONIDASE",
        "PHOSPHOLIPASE",
        "HYALURONIDASE",
        "PHRASEOGRAPHY",
        "EXOPEPTIDASES",
        "SUPERSEDEASES",
        "EASEFULNESSES",
        "NUCLEOTIDASES",
        "PHOSPHOKINASE",
        "PHRASEOLOGIES",
        "SUPRASENSIBLE",
        "HASENPFEFFERS",
        "PENICILLINASE",
        "PHRASEOGRAPHS",
        "DECARBOXYLASE",
        "STEEPLECHASES",
        "THROMBOKINASE",
        "PHRASEOLOGIST",
        "PHOSPHORYLASE",
        "APOCATASTASES",
        "LEISHMANIASES",
        "GALACTOSIDASE",
        "PHRASEMAKINGS",
        "CEASELESSNESS",
        "RIBONUCLEASES",
        "NEURAMINIDASE",
        "ENDOPEPTIDASE",
        "TRANSAMINASES",
        "HELMINTHIASES",
        "STEEPLECHASED",
        "ENDONUCLEASES",
        "HYPOSPADIASES",
        "UNDEREMPHASES",
        "ASPARAGINASES",
        "DEBASEDNESSES",
        "CONTRASEXUALS",
        "ENTEROKINASES",
        "CARBOHYDRASES",
        "COCARBOXYLASE",
        "STREPTOKINASE",
        "DEHYDROGENASE",
        "PARASEXUALITY",
        "TRANSCRIPTASE",
        "POSTVASECTOMY",
        "PHRASEMONGERS",
        "GASEOUSNESSES",
        "STEEPLECHASER",
        "PRASEODYMIUMS",
        "VASECTOMIZING",
        "VASECTOMISING",
        "ELEPHANTIASES"
    ],
    "14": [
        "CYSTOLITHIASES",
        "TELANGIECTASES",
        "SUPRASEGMENTAL",
        "PHRASEOGRAPHIC",
        "HYALURONIDASES",
        "BASELESSNESSES",
        "OXIDOREDUCTASE",
        "GALACTOSIDASES",
        "BRONCHIECTASES",
        "TRICHOMONIASES",
        "ULTRASENSITIVE",
        "CHOLINESTERASE",
        "DEHYDROGENASES",
        "CHOLELITHIASES",
        "PECTINESTERASE",
        "ONCHOCERCIASES",
        "NEURAMINIDASES",
        "PHRASEOLOGISTS",
        "PHOSPHOLIPASES",
        "NEMATODIRIASES",
        "THROMBOKINASES",
        "AMINOPEPTIDASE",
        "DISPLEASEDNESS",
        "COCARBOXYLASES",
        "PENICILLINASES",
        "DISEASEDNESSES",
        "STEEPLECHASERS",
        "STREPTOKINASES",
        "PHOSPHOKINASES",
        "PHRASEOLOGICAL",
        "GLUCURONIDASES",
        "PHOSPHORYLASES",
        "TRANSCRIPTASES",
        "ENDOPEPTIDASES",
        "HEXOSAMINIDASE",
        "BACTERIOSTASES",
        "UNBIASEDNESSES",
        "DISACCHARIDASE",
        "UNPURCHASEABLE",
        "ANTIPERISTASES",
        "DECARBOXYLASES"
    ],
    "15": [
        "DISACCHARIDASES",
        "PATERFAMILIASES",
        "MATERFAMILIASES",
        "SCHISTOSOMIASES",
        "ANKYLOSTOMIASES",
        "HYPOCHONDRIASES",
        "CHOLINESTERASES",
        "CEASELESSNESSES",
        "PECTINESTERASES",
        "AMINOPEPTIDASES",
        "PHRASEMONGERING",
        "OXIDOREDUCTASES",
        "PHRASEOGRAPHIES",
        "ANCYLOSTOMIASES",
        "PARASEXUALITIES",
        "TRYPANOSOMIASES",
        "HEXOSAMINIDASES"
    ]
}