{
    "4": [
        "GEMS"
    ],
    "5": [
        "GEMEL",
        "GEMMY",
        "BEGEM",
        "GEMOT",
        "GEMMA"
    ],
    "6": [
        "GEMOTS",
        "GEMELS",
        "GEMMAN",
        "GEMMAE",
        "GEMMEN",
        "DODGEM",
        "BEGEMS",
        "GEMINY",
        "GEMONY",
        "GEMINI",
        "GEMOTE",
        "GEMMED"
    ],
    "7": [
        "GEMMING",
        "GEMCLIP",
        "GEMMATE",
        "GEMMILY",
        "GEMMIER",
        "GEMSBOK",
        "GEMLIKE",
        "GEMFISH",
        "AGEMATE",
        "DODGEMS",
        "GEMINAL",
        "HEGEMON",
        "GEMOTES",
        "GEMMERY",
        "GEMMULE"
    ],
    "8": [
        "LIEGEMEN",
        "OLIGEMIC",
        "GEMATRIA",
        "GEMMIEST",
        "GEMINIES",
        "AGEMATES",
        "GEMMATED",
        "GEMCLIPS",
        "GEMSBUCK",
        "GEMSHORN",
        "GEMMATES",
        "ARGEMONE",
        "GEMMEOUS",
        "GEMSBOKS",
        "GEMSTONE",
        "HEGEMONS",
        "GEMINATE",
        "BARGEMEN",
        "OLIGEMIA",
        "BIGEMINY",
        "VEGEMITE",
        "GEMINOUS",
        "GEMOLOGY",
        "HEGEMONY",
        "BARGEMAN",
        "FORGEMAN",
        "FORGEMEN",
        "LIEGEMAN",
        "GEMMULES",
        "BEGEMMED"
    ],
    "9": [
        "GEMUTLICH",
        "GEMMATION",
        "GEMMOLOGY",
        "JUDGEMENT",
        "BEGEMMING",
        "LODGEMENT",
        "GEMMERIES",
        "VENGEMENT",
        "GEMSHORNS",
        "GEMMATIVE",
        "GEMSBUCKS",
        "GEMFISHES",
        "ARGEMONES",
        "GEMINALLY",
        "GEMSTONES",
        "VEGEMITES",
        "OLIGEMIAS",
        "GEMINATED",
        "BIGEMINAL",
        "GEMMINESS",
        "HEGEMONIC",
        "BRUMMAGEM",
        "GARAGEMEN",
        "GEMMATING",
        "STRATAGEM",
        "GEMINATES",
        "GEMATRIAS",
        "GARAGEMAN"
    ],
    "10": [
        "ENRAGEMENT",
        "INGEMINATE",
        "GEMINATING",
        "GEMINATION",
        "HEGEMONISM",
        "BIGEMINIES",
        "LODGEMENTS",
        "STRATAGEMS",
        "LARGEMOUTH",
        "JUDGEMENTS",
        "HEGEMONIAL",
        "GEMOLOGIST",
        "HEGEMONIES",
        "ENGAGEMENT",
        "VENGEMENTS",
        "MANGEMANGE",
        "GEMOLOGIES",
        "RAVAGEMENT",
        "TRIGEMINAL",
        "BRUMMAGEMS",
        "MANAGEMENT",
        "GEMMATIONS",
        "GARBAGEMAN",
        "OBLIGEMENT",
        "HEGEMONIST",
        "GARBAGEMEN",
        "AVENGEMENT",
        "GEMMACEOUS",
        "GEMINATELY"
    ],
    "11": [
        "LARGEMOUTHS",
        "GEMMULATION",
        "GEMFIBROZIL",
        "PRESAGEMENT",
        "AVENGEMENTS",
        "GEMMOLOGIST",
        "ADJUDGEMENT",
        "BESIEGEMENT",
        "REVENGEMENT",
        "HEGEMONISTS",
        "TRIGEMINALS",
        "ENGORGEMENT",
        "MANAGEMENTS",
        "ENLARGEMENT",
        "GEMMIPAROUS",
        "ABRIDGEMENT",
        "INGEMINATES",
        "GEMOLOGICAL",
        "OBLIGEMENTS",
        "ENGAGEMENTS",
        "DIVERGEMENT",
        "ARRANGEMENT",
        "GEMINATIONS",
        "DIVULGEMENT",
        "DERANGEMENT",
        "ASSUAGEMENT",
        "IMPINGEMENT",
        "INGEMINATED",
        "GEMMOLOGIES",
        "GEMOLOGISTS",
        "RAVAGEMENTS",
        "WITENAGEMOT",
        "ENRAGEMENTS",
        "UNHINGEMENT",
        "HEGEMONISMS",
        "JUDGEMENTAL",
        "GEMMINESSES",
        "GEMMIFEROUS",
        "BARGEMASTER",
        "HEGEMONICAL"
    ],
    "12": [
        "ADJUDGEMENTS",
        "ASSUAGEMENTS",
        "GEMEINSCHAFT",
        "GEMFIBROZILS",
        "ENVISAGEMENT",
        "INFRINGEMENT",
        "DISGORGEMENT",
        "WITENAGEMOTE",
        "GEMMOLOGISTS",
        "COMANAGEMENT",
        "INGEMINATING",
        "DIVULGEMENTS",
        "ABRIDGEMENTS",
        "SUBMERGEMENT",
        "ARRANGEMENTS",
        "DERANGEMENTS",
        "ESTRANGEMENT",
        "BARGEMASTERS",
        "DIVERGEMENTS",
        "PREJUDGEMENT",
        "REVENGEMENTS",
        "INGEMINATION",
        "WITENAGEMOTS",
        "GEMMULATIONS",
        "MISJUDGEMENT",
        "ENDAMAGEMENT",
        "DISLODGEMENT",
        "MANAGEMENTAL",
        "REENGAGEMENT",
        "UNHINGEMENTS",
        "IMPINGEMENTS",
        "PRESAGEMENTS",
        "ENLARGEMENTS",
        "GEMMOLOGICAL",
        "ENGORGEMENTS",
        "BESIEGEMENTS"
    ],
    "13": [
        "COMANAGEMENTS",
        "REENGAGEMENTS",
        "DISOBLIGEMENT",
        "QUADRIGEMINAL",
        "DISPARAGEMENT",
        "INGEMINATIONS",
        "DISGORGEMENTS",
        "INFRINGEMENTS",
        "ESTRANGEMENTS",
        "WITENAGEMOTES",
        "MISJUDGEMENTS",
        "ENCOURAGEMENT",
        "NONMANAGEMENT",
        "GEMUTLICHKEIT",
        "FOREJUDGEMENT",
        "PREJUDGEMENTS",
        "SUBMERGEMENTS",
        "ENVISAGEMENTS",
        "NONENGAGEMENT",
        "GEMEINSCHAFTS",
        "REARRANGEMENT",
        "SURCHARGEMENT",
        "ENDAMAGEMENTS",
        "DISLODGEMENTS",
        "GEMMIPAROUSLY",
        "MISMANAGEMENT",
        "DISENGAGEMENT"
    ],
    "14": [
        "DISARRANGEMENT",
        "ANTIMANAGEMENT",
        "FOREJUDGEMENTS",
        "GEMUTLICHKEITS",
        "GEMEINSCHAFTEN",
        "DISPARAGEMENTS",
        "QUADRIGEMINATE",
        "SURCHARGEMENTS",
        "ENCOURAGEMENTS",
        "MISARRANGEMENT",
        "NONJUDGEMENTAL",
        "MISMANAGEMENTS",
        "REARRANGEMENTS",
        "DISOBLIGEMENTS",
        "NONENGAGEMENTS",
        "DISCOURAGEMENT",
        "DISENGAGEMENTS",
        "PREARRANGEMENT",
        "QUADRIGEMINOUS"
    ],
    "15": [
        "PREARRANGEMENTS",
        "DISCOURAGEMENTS",
        "MICROMANAGEMENT",
        "MISARRANGEMENTS",
        "NONINFRINGEMENT",
        "INTERCHANGEMENT",
        "DISARRANGEMENTS",
        "ACKNOWLEDGEMENT"
    ]
}