{
    "4": [
        "SCOW",
        "SCOT",
        "SCOP",
        "SCOG"
    ],
    "5": [
        "SCORE",
        "SCOUG",
        "CASCO",
        "SCOGS",
        "SCOOP",
        "SCOTS",
        "SCOWS",
        "SCOLD",
        "SCONE",
        "SCOOT",
        "SCORN",
        "CISCO",
        "SCODY",
        "DISCO",
        "SCOOG",
        "SCOWP",
        "ASCOT",
        "SCOPA",
        "SCOFF",
        "SCOUR",
        "SCOUT",
        "PISCO",
        "SCOPE",
        "SCOWL",
        "ESCOT",
        "SCOUP",
        "SCOPS"
    ],
    "6": [
        "DISCOS",
        "SCONES",
        "ESCORT",
        "SCOPED",
        "FIASCO",
        "SCORER",
        "SCOOGS",
        "SCOOCH",
        "SCOWED",
        "SCORIA",
        "SCOZZA",
        "SCOUPS",
        "SCOPAS",
        "SCOPAE",
        "SCOUGS",
        "SCOOSH",
        "BRASCO",
        "MASCOT",
        "SCOURS",
        "SCOLEX",
        "FRESCO",
        "SCOOTS",
        "CISCOS",
        "SCOFFS",
        "SCOWPS",
        "SCORSE",
        "ROSCOE",
        "SCOLIA",
        "SCOWLS",
        "SCORNS",
        "GASCON",
        "SCONCE",
        "MASCON",
        "SCOTER",
        "SCOUTH",
        "SCORCH",
        "SCOUTS",
        "SCOWTH",
        "SCORED",
        "SCORES",
        "ESCOTS",
        "SCOUSE",
        "SCOPES",
        "ASCOTS",
        "SCOOPS",
        "CASCOS",
        "SCOLDS",
        "PISCOS",
        "SCOOBY",
        "SCOTIA",
        "SCOTCH"
    ],
    "7": [
        "FUSCOUS",
        "TEDESCO",
        "VISCOID",
        "SCORSER",
        "SCOFFER",
        "SCOPATE",
        "ABSCOND",
        "GASCONS",
        "ESCOTED",
        "SCOUSES",
        "SCOTOMA",
        "SCOZZAS",
        "SCOGGED",
        "BRASCOS",
        "SCONCES",
        "SCOURSE",
        "SCORNER",
        "SCORPER",
        "MASCONS",
        "ASCONCE",
        "SCOTERS",
        "SCOWING",
        "SCOFFED",
        "FIASCOS",
        "SCORSED",
        "SCOPULA",
        "SCOUSER",
        "BESCOUR",
        "SCOOTED",
        "SCODIER",
        "SCOWDER",
        "SCOLION",
        "MUSCOID",
        "SCORIAC",
        "VISCOSE",
        "DISCOID",
        "MISCOPY",
        "ESCORTS",
        "RESCORE",
        "SCOLDED",
        "SCOLDER",
        "PEASCOD",
        "DISCOED",
        "VISCOUS",
        "SCOTTIE",
        "SCONCED",
        "SCOOTER",
        "SCOUPED",
        "SCOWLED",
        "MISCODE",
        "SCOOGED",
        "SCOWTHS",
        "SCOURIE",
        "SCOTIAS",
        "SCOWLER",
        "SCORING",
        "MISCOOK",
        "MORISCO",
        "FRESCOS",
        "SCOUTHS",
        "MASCOTS",
        "MUSCOSE",
        "SCORERS",
        "SCORIFY",
        "SCOLLOP",
        "SCORNED",
        "DISCOER",
        "SCOTOMY",
        "SCOOTCH",
        "SCORIAE",
        "SCOURGE",
        "SCOUGED",
        "ESCOLAR",
        "SCOPING",
        "MUSCONE",
        "ROSCOES",
        "SCOUTED",
        "SCOURER",
        "CISCOES",
        "SCOWPED",
        "SCOWRER",
        "SCORSES",
        "MISCOIN",
        "SCOOPER",
        "SCOWRIE",
        "SCOOPED",
        "SCOUTER",
        "DISCORD",
        "SCOURED",
        "MUDSCOW"
    ],
    "8": [
        "SCORPERS",
        "SCOOPFUL",
        "CHUBASCO",
        "DISCORDS",
        "OUTSCOLD",
        "ESCOLARS",
        "MISCODES",
        "PEASCODS",
        "SCORDATO",
        "SCOOSHES",
        "SCOTCHES",
        "DISCOING",
        "SCORINGS",
        "DISCOURE",
        "SCOWRERS",
        "MISCODED",
        "RESCORES",
        "SCOGGING",
        "SCOPULAS",
        "WAINSCOT",
        "SCOTOPIC",
        "SCOOPING",
        "OUTSCORN",
        "DISCOUNT",
        "SCOLIOMA",
        "BARBASCO",
        "SCOFFERS",
        "SCOWDERS",
        "SCOUSERS",
        "DISCOERS",
        "OUTSCORE",
        "SCOOPERS",
        "SCOOCHES",
        "ENSCONCE",
        "SCOUTING",
        "SCOTOMAS",
        "VISCOUNT",
        "MISCOUNT",
        "SCORCHES",
        "SCOURING",
        "ESCOTING",
        "SCOLYTID",
        "SCOUGING",
        "OTOSCOPY",
        "EPISCOPE",
        "BIOSCOPE",
        "SIXSCORE",
        "EPISCOPY",
        "SCORNERS",
        "SCOTOMIA",
        "SCOWRIES",
        "SCONCING",
        "ONISCOID",
        "MISCOINS",
        "ATAMASCO",
        "SCORSING",
        "SCORIOUS",
        "SCOINSON",
        "SCORNING",
        "FRESCOER",
        "FRESCOED",
        "SCOWLING",
        "SCOLICES",
        "MISCOOKS",
        "SCOOBIES",
        "SCOLECID",
        "ASCOCARP",
        "FIASCOES",
        "SCOOGING",
        "SCOMBRID",
        "MORISCOS",
        "SCORCHER",
        "SCORSERS",
        "DISCOLOR",
        "PRESCORE",
        "BESCOURS",
        "SCOTTIES",
        "SCOURSES",
        "SCORPION",
        "SCOLDERS",
        "SCOPULAE",
        "SCOUTERS",
        "BISCOTTO",
        "SCOURIES",
        "SCOOTERS",
        "DISCOVER",
        "SCOURGES",
        "SCOPELID",
        "SCOUPING",
        "SCOFFLAW",
        "FRESCOES",
        "VISCOSES",
        "MUDSCOWS",
        "SCOLDING",
        "MUSCONES",
        "BIOSCOPY",
        "SCOREPAD",
        "DIASCOPE",
        "BESCORCH",
        "OUTSCOOP",
        "ALFRESCO",
        "SCOTOPIA",
        "COUSCOUS",
        "ASCORBIC",
        "INSCONCE",
        "SCORCHED",
        "RESCORED",
        "SCODIEST",
        "SCOOTING",
        "SCOWTHER",
        "OTOSCOPE",
        "SCOOCHED",
        "SCOWLERS",
        "MYOSCOPE",
        "SCOMFISH",
        "SCOLLOPS",
        "SCOUTHER",
        "ABSCONDS",
        "MISCOLOR",
        "SCONTION",
        "SEASCOUT",
        "SCOTCHED",
        "BISCOTTI",
        "ZOOSCOPY",
        "UROSCOPY",
        "SCOLECES",
        "SCOURSED",
        "SCORNFUL",
        "SCOURGED",
        "ESCOTTED",
        "SCOURGER",
        "SCOOSHED",
        "DISCOIDS",
        "ESCORTED",
        "SCOWPING",
        "SCOFFING",
        "SCOURERS",
        "IRISCOPE"
    ],
    "9": [
        "ASCOSPORE",
        "FETOSCOPE",
        "SCOLYTOID",
        "GASCONISM",
        "MISCODING",
        "HOPSCOTCH",
        "GAUCHESCO",
        "UROSCOPIC",
        "HODOSCOPE",
        "COCKSCOMB",
        "ZOOSCOPIC",
        "DISCOURSE",
        "NINESCORE",
        "ENGISCOPE",
        "SCOLDABLE",
        "KONISCOPE",
        "PYROSCOPE",
        "SCORCHERS",
        "SCOLIOTIC",
        "ABSCONDER",
        "SCOOPFULS",
        "VISCOSITY",
        "ENDOSCOPE",
        "SCOPELIDS",
        "TELESCOPY",
        "SCOOTCHED",
        "CRYOSCOPY",
        "MORISCOES",
        "SCORPIONS",
        "AUTOSCOPY",
        "SCOLLOPED",
        "SCOURSING",
        "MISCOPIED",
        "SCOFFLAWS",
        "RESCORING",
        "SCOMBROID",
        "LOBSCOUSE",
        "SCORIFIES",
        "SCOLIOMAS",
        "PIGSCONCE",
        "ENSCONCED",
        "ASCORBATE",
        "SCOMBRIDS",
        "MISCOINED",
        "SCOTOMATA",
        "DISCOVERT",
        "OTOSCOPES",
        "FRESCOIST",
        "OUROSCOPY",
        "MISCOLORS",
        "DISCOIDAL",
        "EPISCOPAL",
        "ENDOSCOPY",
        "SOMASCOPE",
        "SCOURGING",
        "SCOFFINGS",
        "CHUBASCOS",
        "DISCOMFIT",
        "SCOOTCHES",
        "ESCOPETTE",
        "EPISCOPES",
        "SCORODITE",
        "POROSCOPE",
        "CRYOSCOPE",
        "SCORBUTIC",
        "PRESCORED",
        "SIXSCORES",
        "AURISCOPE",
        "OUTSCOOPS",
        "ESCOTTING",
        "SCONTIONS",
        "FRESCOERS",
        "ENGYSCOPE",
        "INSCONCED",
        "MISCOPIES",
        "MUSCOLOGY",
        "SCOURINGS",
        "SCOLIOSIS",
        "GASCONADE",
        "SCOINSONS",
        "DISCOBOLI",
        "WAINSCOTS",
        "SCOUTHERS",
        "SCOLECOID",
        "SCOTOMIAS",
        "TELESCOPE",
        "UNSCOURED",
        "DISCOLOGY",
        "SCOLIOSES",
        "OUTSCORES",
        "OUTSCORED",
        "SCOWDERED",
        "SCOWTHERS",
        "SCORPIOID",
        "OUTSCORNS",
        "SCOUTINGS",
        "SCORELESS",
        "MISCOLOUR",
        "SCOUNDREL",
        "ATAMASCOS",
        "SCOLECITE",
        "LAMBRUSCO",
        "DIASCOPES",
        "ESCORTAGE",
        "MISCOUNTS",
        "SCOOCHING",
        "ASCOCARPS",
        "INSCONCES",
        "VISCOUNTS",
        "ENSCONCES",
        "MUTOSCOPE",
        "AYAHUASCO",
        "DISCOUNTS",
        "MYOSCOPES",
        "SCOPOLINE",
        "SCORNINGS",
        "SCOREPADS",
        "IRISCOPES",
        "SCORCHING",
        "HOROSCOPY",
        "SCORELINE",
        "BIOSCOPES",
        "DISCOLOUR",
        "BARBASCOS",
        "SCOLECIDS",
        "BESCOURED",
        "SCONCHEON",
        "POROSCOPY",
        "DISCOLORS",
        "AEROSCOPE",
        "ASCOGONIA",
        "MEGASCOPE",
        "VISCOUSLY",
        "KINESCOPE",
        "SEASCOUTS",
        "SCORECARD",
        "PERISCOPE",
        "DISCOURES",
        "VITASCOPE",
        "PRESCORES",
        "SCOTCHING",
        "SKIASCOPE",
        "SCOOPABLE",
        "FETOSCOPY",
        "DISCOURED",
        "FRESCOING",
        "DISCOMMON",
        "FOURSCORE",
        "SCOOPINGS",
        "SKIASCOPY",
        "BORESCOPE",
        "SCOLYTIDS",
        "ABSCONDED",
        "SCOLDINGS",
        "SCOTOMIES",
        "VISCOIDAL",
        "HOROSCOPE",
        "OTOSCOPIC",
        "SCORIFIED",
        "VISCOUNTY",
        "SCOPULATE",
        "SCOUTHERY",
        "MUSCOVADO",
        "SCOOPSFUL",
        "SCORRENDO",
        "GYROSCOPE",
        "DISCOVERY",
        "SCOTOPHIL",
        "SCOOSHING",
        "DISCOVERS",
        "OUTSCOLDS",
        "OVERSCORE",
        "SCORIFIER",
        "BAROSCOPE",
        "SCOURGERS",
        "MISCOOKED",
        "ESCORTING",
        "MENISCOID",
        "MUSCOVITE",
        "MANOSCOPY",
        "SCOTOPIAS",
        "DISCORDED",
        "SCOPELOID"
    ],
    "10": [
        "PERISCOPES",
        "LACTOSCOPE",
        "UROSCOPIES",
        "POROSCOPES",
        "BIOSCOPIES",
        "MISCOLORED",
        "ENGYSCOPES",
        "INSCONCING",
        "ENSCONCING",
        "OUTSCORNED",
        "RHINOSCOPY",
        "SCOUTCRAFT",
        "EPISCOPANT",
        "FOURSCORTH",
        "GASCONADER",
        "ENDOSCOPES",
        "PERISCOPIC",
        "KINESCOPED",
        "RADIOSCOPE",
        "DISCOBOLUS",
        "VISCOUNTCY",
        "TRINISCOPE",
        "STATOSCOPE",
        "NONVISCOUS",
        "ASCORBATES",
        "DISCORDFUL",
        "MUTOSCOPES",
        "DISCOMPOSE",
        "BESCORCHED",
        "SCOLLOPING",
        "CRYOSCOPIC",
        "PHASCOGALE",
        "SCOREBOARD",
        "SCORECARDS",
        "MISCONNECT",
        "MISCONSTER",
        "MISCORRECT",
        "SCOUTHERED",
        "GONIOSCOPE",
        "COCKSCOMBS",
        "BAROSCOPIC",
        "TELESCOPED",
        "EPISCOPISE",
        "DISCOPHILE",
        "PIGSCONCES",
        "ESCORTAGES",
        "RADIOSCOPY",
        "FIBERSCOPE",
        "CROSSCOURT",
        "MUSCOVADOS",
        "HOROSCOPIC",
        "CRYOSCOPES",
        "EPISCOPIZE",
        "SCOFFINGLY",
        "NINESCORES",
        "MISCOLOURS",
        "DISCORDING",
        "RHINOSCOPE",
        "SCORODITES",
        "SCORESHEET",
        "OUTSCOLDED",
        "ZOOSCOPIES",
        "DISCOMFORT",
        "PANTOSCOPE",
        "FRESCOINGS",
        "SCOWDERING",
        "HAGIOSCOPE",
        "FOETOSCOPY",
        "UNDERSCORE",
        "KINESCOPES",
        "ABSCONDING",
        "SCOOTERIST",
        "DISCORDANT",
        "DISCOURING",
        "MOLLUSCOUS",
        "ASCOCARPIC",
        "DISCOBOLOS",
        "UROSCOPIST",
        "BAROSCOPES",
        "CYSTOSCOPY",
        "EPISCOPATE",
        "OVERSCORES",
        "DISCOVERED",
        "BORESCOPES",
        "MEGASCOPIC",
        "DISCONCERT",
        "SCORNFULLY",
        "REDISCOUNT",
        "ASCOSPORIC",
        "SCOUNDRELS",
        "UNSCORCHED",
        "HIEROSCOPY",
        "SCORDATURA",
        "OTOSCOPIES",
        "URINOSCOPY",
        "SCOLDINGLY",
        "DISCOLOURS",
        "SKIASCOPES",
        "VITASCOPES",
        "BESCORCHES",
        "DISCOUNTED",
        "REDISCOVER",
        "EPISCOPIES",
        "TELESCOPES",
        "SUBFUSCOUS",
        "DISCOLORED",
        "NIGHTSCOPE",
        "SCOLYTOIDS",
        "SCORPIOIDS",
        "MYRIOSCOPE",
        "MISCONCEIT",
        "COUSCOUSES",
        "SCOOTCHING",
        "BARBASCOES",
        "SUPERSCOUT",
        "MISCOINING",
        "PYROSCOPES",
        "GYROSCOPES",
        "SCORIFYING",
        "MOLLUSCOID",
        "WAINSCOTED",
        "SCORIFIERS",
        "ORTHOSCOPE",
        "EPISCOPACY",
        "COUSCOUSOU",
        "SCOPOLINES",
        "AEROSCOPES",
        "UNESCORTED",
        "GASCONISMS",
        "FIBRESCOPE",
        "SCORELINES",
        "DISCOMMODE",
        "ASCOMYCETE",
        "SCORPIONIC",
        "DISCONTENT",
        "OUTSCORING",
        "LAMBRUSCOS",
        "RADARSCOPE",
        "SCOLECITES",
        "FRESCOISTS",
        "MUSCOVITES",
        "SCORPAENID",
        "SCONCHEONS",
        "FETOSCOPES",
        "ICONOSCOPE",
        "AURISCOPIC",
        "OUTSCOOPED",
        "MEGASCOPES",
        "ASCOSPORES",
        "CODISCOVER",
        "DISCOURSER",
        "DISCOMMONS",
        "SCOMFISHES",
        "MISCONTENT",
        "PHONOSCOPE",
        "DISCONFIRM",
        "VISCOMETER",
        "GASCONADED",
        "MISCOUNSEL",
        "DISCOMMEND",
        "ENGISCOPES",
        "COLPOSCOPE",
        "OVERSCORED",
        "MISCOMPUTE",
        "SCORCHINGS",
        "MISCONDUCT",
        "AUTOSCOPIC",
        "CYSTOSCOPE",
        "THREESCORE",
        "AYAHUASCOS",
        "SCORZONERA",
        "DISCONNECT",
        "ANEMOSCOPE",
        "SCOWTHERED",
        "BESCOURING",
        "MICROSCOPY",
        "GYROSCOPIC",
        "OBELISCOID",
        "DISCOVERER",
        "DISCOMFITS",
        "ESCOPETTES",
        "HOROSCOPES",
        "TELESCOPIC",
        "COLPOSCOPY",
        "PRESCORING",
        "DISCOUNTER",
        "HELIOSCOPE",
        "SCOPELOIDS",
        "HODOSCOPES",
        "SCOTODINIA",
        "SOMASCOPES",
        "KONISCOPES",
        "MISCOUNTED",
        "TEINOSCOPE",
        "GASCONADES",
        "MISCOPYING",
        "POROSCOPIC",
        "DISCOURSED",
        "DISCONSENT",
        "DISCOURAGE",
        "EIGHTSCORE",
        "HYGROSCOPE",
        "DISCOURSES",
        "DISCOURSAL",
        "SCOMBROIDS",
        "VISCOMETRY",
        "SCOWLINGLY",
        "AURISCOPES",
        "MISCOOKING",
        "SCOMFISHED",
        "LOBSCOUSES",
        "HYDROSCOPE",
        "NEPHOSCOPE",
        "ENDOSCOPIC",
        "DISCOUNSEL",
        "NECROSCOPY",
        "ASCOGONIUM",
        "ABSCONDERS",
        "SCOTOMETER",
        "MICROSCOPE"
    ],
    "11": [
        "METOPOSCOPY",
        "SCORDATURAS",
        "MANOSCOPIES",
        "UROSCOPISTS",
        "MISCONSTERS",
        "OUTSCOLDING",
        "OUTSCOOPING",
        "ARTHROSCOPE",
        "PHONOSCOPES",
        "STROBOSCOPE",
        "EPISCOPATES",
        "TELESCOPING",
        "HYGROSCOPIC",
        "AUTOSCOPIES",
        "ARTHROSCOPY",
        "DISCOUNTERS",
        "VISCOSITIES",
        "HEPATOSCOPY",
        "RETINOSCOPE",
        "SCORESHEETS",
        "SCOPOPHILIA",
        "DISCOGRAPHY",
        "SCOTOMATOUS",
        "PANTOSCOPES",
        "SUPERSCOUTS",
        "LACTOSCOPES",
        "SCOREKEEPER",
        "SCORCHINGLY",
        "MISCOUNTING",
        "MACROSCOPIC",
        "DISCOPHORAN",
        "NIGHTSCOPES",
        "REDISCOUNTS",
        "DISCOURAGES",
        "GYROSCOPICS",
        "ENDOSCOPIES",
        "VISCOUNTIES",
        "PROCTOSCOPE",
        "DISCONTENTS",
        "KINESCOPING",
        "MISCONCEIVE",
        "DISCOMFORTS",
        "RETINOSCOPY",
        "RHINOSCOPIC",
        "EPISCOPANTS",
        "MICROSCOPES",
        "EPISCOPIZES",
        "THERMOSCOPE",
        "DISCOTHEQUE",
        "CRYOSCOPIES",
        "SEISMOSCOPE",
        "MISCONNECTS",
        "REDISCOVERS",
        "DISCOURSERS",
        "SCORPAENIDS",
        "STEREOSCOPY",
        "UNDERSCORED",
        "ORTHOSCOPES",
        "STEREOSCOPE",
        "EPISCOPIZED",
        "FIBRESCOPES",
        "SCOPOPHOBIA",
        "HOPSCOTCHES",
        "GIRDLESCONE",
        "DISCOMPOSED",
        "MISCOMPUTED",
        "STETHOSCOPE",
        "CRANIOSCOPY",
        "MISCOMPUTES",
        "DISCOLOGIST",
        "DISCONSENTS",
        "DISCONFIRMS",
        "GASCONADERS",
        "WAINSCOTTED",
        "WAINSCOTING",
        "DISCOMFITED",
        "DISCOMMENDS",
        "MISCOLORING",
        "DISCOMMODES",
        "BESCORCHING",
        "GASTROSCOPE",
        "SNIPERSCOPE",
        "NEPHROSCOPY",
        "HYDROSCOPIC",
        "ENDOSCOPIST",
        "FLUOROSCOPY",
        "MUSCOLOGIES",
        "SCOPOPHILIC",
        "SCOREBOARDS",
        "PROCTOSCOPY",
        "ANEMOSCOPES",
        "FIBERSCOPES",
        "HOROSCOPIST",
        "SCORZONERAS",
        "DISCOMYCETE",
        "DISCORDANCY",
        "DISCOVERERS",
        "NONDISCOUNT",
        "OUTSCORNING",
        "EPISCOPISED",
        "RHINOSCOPES",
        "MICROSCOPIC",
        "VISCOUSNESS",
        "DISCOMFITER",
        "GASTROSCOPY",
        "MISCORRECTS",
        "ICONOSCOPES",
        "EPIDIASCOPE",
        "MISCOLOURED",
        "SCOUTCRAFTS",
        "LYCHNOSCOPE",
        "SCOMFISHING",
        "OUROSCOPIES",
        "MISCONTENTS",
        "THREESCORES",
        "EPISCOPATED",
        "CYSTOSCOPES",
        "TELESCOPIST",
        "MISCONDUCTS",
        "STATOSCOPES",
        "MISCONCEITS",
        "DISCOMMONED",
        "DISCOUNSELS",
        "RADARSCOPES",
        "DISCOMMODED",
        "COLPOSCOPES",
        "ONEIROSCOPY",
        "DISCOMPOSES",
        "MOLLUSCOIDS",
        "DIASCORDIUM",
        "FLUOROSCOPE",
        "SCORIACEOUS",
        "VISCOUNTESS",
        "HOROSCOPIES",
        "EIGHTSCORES",
        "DISCONNECTS",
        "DISCOVERIES",
        "FETOSCOPIES",
        "CYSTOSCOPIC",
        "LAPAROSCOPY",
        "STETHOSCOPY",
        "NEPHROSCOPE",
        "SCOOTERISTS",
        "HELIOSCOPES",
        "SCOTODINIAS",
        "GONIOSCOPES",
        "RADIOSCOPIC",
        "HOPSCOTCHED",
        "SCORPAENOID",
        "UNDERSCORES",
        "CHRONOSCOPE",
        "DISCONCERTS",
        "RADIOSCOPES",
        "HAGIOSCOPES",
        "COUSCOUSOUS",
        "SCOUNDRELLY",
        "MYRIOSCOPES",
        "NEPHOSCOPES",
        "CODISCOVERS",
        "TRINISCOPES",
        "DICHROSCOPE",
        "REDISCOVERY",
        "EPISCOPISES",
        "TELESCOPIES",
        "DISCOURAGED",
        "DISCOURSIVE",
        "MISCOUNSELS",
        "HYDROSCOPES",
        "MISCONSTRUE",
        "SCOUTHERING",
        "ASCOMYCETES",
        "OPEIDOSCOPE",
        "VECTORSCOPE",
        "SCOUTMASTER",
        "HELIOSCOPIC",
        "BENTHOSCOPE",
        "POROSCOPIES",
        "COLONOSCOPE",
        "DISCOURAGER",
        "TEINOSCOPES",
        "LAPAROSCOPE",
        "PHASCOGALES",
        "COLONOSCOPY",
        "DISCOVERING",
        "GASCONADING",
        "NECROSCOPIC",
        "SCOTOMETERS",
        "VISCOMETERS",
        "SCOLOPENDRA",
        "SCOWTHERING",
        "KINETOSCOPE",
        "OVERSCORING",
        "DISCOLOGIES",
        "CHROMOSCOPE",
        "CRESCOGRAPH",
        "EPISCOPALLY",
        "HAGIOSCOPIC",
        "ORTHOSCOPIC",
        "POLARISCOPE",
        "DISCONTINUE",
        "ABSCONDENCE",
        "VISCOMETRIC",
        "DISCOPHILES",
        "OFFSCOURING",
        "SCOWDERINGS",
        "STAUROSCOPE",
        "SKIASCOPIES",
        "DISCOLORING",
        "DISCORDANCE",
        "HYGROSCOPES",
        "SCOPOLAMINE",
        "SCOLECIFORM",
        "DISCOLOURED",
        "DISCOURTESY",
        "DISCOUNTING",
        "PSEUDOSCOPE",
        "DISCOURSING",
        "PANTOSCOPIC"
    ],
    "12": [
        "COLONOSCOPES",
        "REDISCOUNTED",
        "DISCONNECTED",
        "LAPAROSCOPIC",
        "DISCOMFITURE",
        "RHINOSCOPIES",
        "EPISCOPIZING",
        "URETHROSCOPY",
        "DISCONFIRMED",
        "KINETOSCOPES",
        "EPISCOPACIES",
        "ENDOSCOPISTS",
        "REDISCOVERER",
        "DISCOURTEISE",
        "STROBOSCOPES",
        "OVERDISCOUNT",
        "DISCOMMUNITY",
        "SCOPTOPHOBIA",
        "DACTYLOSCOPY",
        "BRONCHOSCOPY",
        "SCOPOLAMINES",
        "REDISCOVERED",
        "WAINSCOTINGS",
        "TRACHEOSCOPY",
        "ARTHROSCOPIC",
        "STEREOSCOPIC",
        "THORACOSCOPE",
        "MISCONCEIVED",
        "DISCONTINUES",
        "UNDISCORDANT",
        "EPISCOPISING",
        "POLARISCOPES",
        "JURISCONSULT",
        "DISCOPHOROUS",
        "SCOPOPHILIAS",
        "DISCONNEXION",
        "SNIPERSCOPES",
        "DIASCORDIUMS",
        "MISCONNECTED",
        "DISCONSOLATE",
        "FLUOROSCOPES",
        "UNSCOTTIFIED",
        "BRONCHOSCOPE",
        "URINOSCOPIES",
        "POLARISCOPIC",
        "DISCOVERTURE",
        "EPISCOPALISM",
        "PREDISCOVERY",
        "DISCOMPOSING",
        "HOPSCOTCHING",
        "DISCORDANTLY",
        "CHROMOSCOPES",
        "SCOUTHERINGS",
        "DISCOGRAPHER",
        "DISCOLORMENT",
        "KALEIDOSCOPE",
        "AETHRIOSCOPE",
        "STEREOSCOPES",
        "DISCOBOLUSES",
        "LARYNGOSCOPE",
        "BENTHOSCOPES",
        "DISCOMMODITY",
        "HOROSCOPISTS",
        "MISCONSTRUCT",
        "CODISCOVERER",
        "PRAXINOSCOPE",
        "SCOLOPENDRID",
        "PROCTOSCOPIC",
        "VISCOUNTCIES",
        "DEUTEROSCOPY",
        "DISCORPORATE",
        "ISOTENISCOPE",
        "FLUOROSCOPED",
        "ARTHROSCOPES",
        "DICHROOSCOPE",
        "MISCOLOURING",
        "SCOLOPENDRAS",
        "VISCOELASTIC",
        "DISCOLOURING",
        "SCOPTOPHILIA",
        "BUTTERSCOTCH",
        "DISCOURAGERS",
        "LAPAROSCOPES",
        "URETHROSCOPE",
        "EPIDIASCOPES",
        "DISCOVERABLE",
        "SYNCHROSCOPE",
        "UNDISCOVERED",
        "SCOUTMASTERS",
        "FOETOSCOPIES",
        "DISCOUNTABLE",
        "OPEIDOSCOPES",
        "MISCONDUCTED",
        "THERMOSCOPIC",
        "ABSCONDENCES",
        "EPISCOPALIAN",
        "DISCOMMENDED",
        "OFFSCOURINGS",
        "METOPOSCOPIC",
        "SCORPAENOIDS",
        "PROCTOSCOPES",
        "DISCONSENTED",
        "CODISCOVERED",
        "DISCONTENTED",
        "DISCOMFITING",
        "DISCOURAGING",
        "DICHROISCOPE",
        "EPISCOPATING",
        "GALVANOSCOPY",
        "GASTROSCOPES",
        "VISCOSIMETER",
        "SPECTROSCOPY",
        "MISCONCEIVER",
        "SCOPOPHOBIAS",
        "MOLLUSCOIDAL",
        "RETINOSCOPIC",
        "DISCORDANCES",
        "DISCONTINUER",
        "VISCOSIMETRY",
        "NEPHROSCOPES",
        "DISCOMYCETES",
        "MISCONSTRUES",
        "GASTROSCOPIC",
        "GALVANOSCOPE",
        "SCOLOPACEOUS",
        "STAUROSCOPES",
        "MISCONSTRUED",
        "DISCOURTEOUS",
        "MISCONCEIVES",
        "SEISMOSCOPIC",
        "EBULLIOSCOPE",
        "SCORNFULNESS",
        "MICROSCOPIST",
        "UNDISCORDING",
        "VISCOUNTSHIP",
        "MISCONCEITED",
        "MICROSCOPIES",
        "MISCONSTERED",
        "MYRINGOSCOPE",
        "DISCOMPOSURE",
        "STETHOSCOPES",
        "TELESCOPICAL",
        "DISCOMFITERS",
        "STAUROSCOPIC",
        "WAINSCOTTING",
        "LARYNGOSCOPY",
        "DISCOMEDUSAN",
        "DISCOLOGISTS",
        "ASCOMYCETOUS",
        "NECROSCOPIES",
        "STETHOSCOPIC",
        "STROBOSCOPIC",
        "CYSTOSCOPIES",
        "DISCOTHEQUES",
        "DISCOMFORTED",
        "DISCOMMONING",
        "PSEUDOSCOPES",
        "DISCONTINUED",
        "LYCHNOSCOPES",
        "ORNITHOSCOPY",
        "RETINOSCOPES",
        "EBULLIOSCOPY",
        "THERMOSCOPES",
        "SPHYGMOSCOPE",
        "CHRONOSCOPIC",
        "VISCOMETRIES",
        "ELECTROSCOPE",
        "FLUOROSCOPIC",
        "VECTORSCOPES",
        "DISCOPHORANS",
        "DISCONCERTED",
        "UNDERSCORING",
        "DICHROSCOPES",
        "SEISMOSCOPES",
        "RADIOSCOPIES",
        "TELESCOPISTS",
        "SNOOPERSCOPE",
        "MISCORRECTED",
        "CHRONOSCOPES",
        "SCOREKEEPERS",
        "MISCOMPUTING",
        "SPECTROSCOPE",
        "HIEROSCOPIES",
        "DISCOGRAPHIC",
        "OSCILLOSCOPE",
        "CRESCOGRAPHS",
        "SCOPOPHILIAC",
        "DISCONNECTER",
        "DICHROSCOPIC",
        "MISCONTENTED",
        "GIRDLESCONES",
        "COLPOSCOPIES",
        "DISCOMMODING"
    ],
    "13": [
        "REDISCOUNTING",
        "CODISCOVERING",
        "DISCONNECTING",
        "EBULLIOSCOPIC",
        "ISOTENISCOPES",
        "UNDISCOMFITED",
        "DICHROISCOPES",
        "EPISCOPALIANS",
        "ELECTROSCOPIC",
        "OMOPLATOSCOPY",
        "LARYNGOSCOPES",
        "RETINOSCOPIES",
        "DISCONSENTING",
        "DISCOURTESIES",
        "STETHOSCOPIST",
        "DISCOLORATION",
        "TACHISTOSCOPE",
        "GALVANOSCOPES",
        "HEPATOSCOPIES",
        "OSCILLOSCOPES",
        "DISCOLORMENTS",
        "ELECTROSCOPES",
        "SCORBUTICALLY",
        "DEUTEROSCOPIC",
        "JURISCONSULTS",
        "DICHROOSCOPES",
        "SPHYGMOSCOPES",
        "VISCOSIMETRIC",
        "LAPAROSCOPIES",
        "METOPOSCOPIES",
        "REDISCOVERIES",
        "SPECTROSCOPIC",
        "CRANIOSCOPIST",
        "VISCOUSNESSES",
        "SCOPTOPHOBIAS",
        "DISCOMFITURES",
        "DISCONNEXIONS",
        "SCORCHINGNESS",
        "MISCONCEPTION",
        "DISCONTINUITY",
        "MISCONCEIVERS",
        "PHARYNGOSCOPE",
        "VISCOSIMETERS",
        "MISCOMPREHEND",
        "REDISCOVERING",
        "GASTROSCOPIST",
        "DICHROISCOPIC",
        "ANTISCORBUTIC",
        "DISCONTIGUOUS",
        "FLUOROSCOPIST",
        "MISCONNECTION",
        "KALEIDOSCOPES",
        "DISCOMPOSEDLY",
        "MISCORRECTION",
        "RONTGENOSCOPE",
        "STEREOSCOPIES",
        "REDISCOVERERS",
        "LARYNGOSCOPIC",
        "SNOOPERSCOPES",
        "NEPHROSCOPIES",
        "DISCONNECTION",
        "DISCONTINUOUS",
        "DISCOMYCETOUS",
        "EPISCOPALISMS",
        "MICROSCOPICAL",
        "UNDISCOURAGED",
        "MISCONJECTURE",
        "MISCONCEITING",
        "DISCONCERTION",
        "DISCOLOURMENT",
        "MISCONSTRUING",
        "VISCOUNTESSES",
        "COLPOSCOPICAL",
        "DISCONFIRMING",
        "DISCOURAGINGS",
        "URETHROSCOPES",
        "SCORIFICATION",
        "MYRINGOSCOPES",
        "PRAXINOSCOPES",
        "MISCONDUCTING",
        "VISCOMETRICAL",
        "METOPOSCOPIST",
        "MISCONSTRUCTS",
        "MICROSCOPISTS",
        "RONTGENOSCOPY",
        "THORACOSCOPES",
        "CHOREPISCOPAL",
        "FLUOROSCOPING",
        "CODISCOVERERS",
        "OSCILLOSCOPIC",
        "KALEIDOSCOPIC",
        "DISCONTENTING",
        "VISCOUNTSHIPS",
        "TELESCOPIFORM",
        "PROCTOSCOPIES",
        "PHONENDOSCOPE",
        "DISCONNECTERS",
        "DIPLEIDOSCOPE",
        "DISCOMEDUSANS",
        "STEREOSCOPIST",
        "GASTROSCOPIES",
        "MISCONNECTING",
        "BRONCHOSCOPES",
        "DISCORDANCIES",
        "WAINSCOTTINGS",
        "PHARYNGOSCOPY",
        "AETHRIOSCOPES",
        "DISCONTINUERS",
        "GALVANOSCOPIC",
        "SIGMOIDOSCOPY",
        "BRONCHOSCOPIC",
        "DISCOMMENDING",
        "LAPAROSCOPIST",
        "ARTHROSCOPIES",
        "ONEIROSCOPIES",
        "DISCOUNSELLED",
        "DISCOVERTURES",
        "NECROSCOPICAL",
        "FLUOROSCOPIES",
        "SCOLOPENDRINE",
        "DISCOMMODIOUS",
        "SCOLOPENDRIUM",
        "SPECTROSCOPES",
        "RETINOSCOPIST",
        "COLONOSCOPIES",
        "MISCOUNSELLED",
        "OVERDISCOUNTS",
        "STETHOSCOPIES",
        "DISCONFORMITY",
        "DISCONNECTIVE",
        "DISCONTIGUITY",
        "SCOLOPENDRIDS",
        "MISCORRECTING",
        "DISCOMMISSION",
        "MISCONCEIVING",
        "SIGMOIDOSCOPE",
        "DISCONCERTING",
        "MISCONSTERING",
        "ONEIROSCOPIST",
        "URETHROSCOPIC",
        "DISCOMPOSURES",
        "HYGROSCOPICAL",
        "ESOPHAGOSCOPE",
        "CRANIOSCOPIES",
        "SCOPOPHILIACS",
        "EBULLIOSCOPES",
        "HYDROSCOPICAL",
        "SYNCHROSCOPES",
        "DISCOGRAPHERS",
        "DISCONTINUING",
        "DICHROOSCOPIC",
        "SCOPTOPHILIAS",
        "MISCONTENTING",
        "DISCOGRAPHIES",
        "DISCONTENTFUL",
        "DISCOMFORTING"
    ],
    "14": [
        "DISCOMFORTABLE",
        "DISCONSOLATION",
        "SCORIFICATIONS",
        "PERISCOPICALLY",
        "PHOSPHOROSCOPE",
        "DISCOLOURMENTS",
        "STEREOSCOPICAL",
        "ORNITHOSCOPIES",
        "SCOLOPENDRIUMS",
        "DISCOLOURATION",
        "GASTROSCOPISTS",
        "TELESCOPICALLY",
        "RONTGENOSCOPES",
        "STETHOSCOPISTS",
        "NONHYGROSCOPIC",
        "DISCONTINUANCE",
        "LARYNGOSCOPIST",
        "SCINTILLOSCOPE",
        "SUBMICROSCOPIC",
        "EBULLIOSCOPIES",
        "DISCOLORATIONS",
        "MISCONCEPTIONS",
        "HYPERVISCOSITY",
        "OESOPHAGOSCOPY",
        "ROENTGENOSCOPE",
        "URETHROSCOPIES",
        "PSEUDOSCORPION",
        "HYGROSCOPICITY",
        "RETINOSCOPISTS",
        "TRACHEOSCOPIES",
        "MISCONTENTMENT",
        "DISCOMBOBULATE",
        "ANAMORPHOSCOPE",
        "BRONCHOSCOPIES",
        "GYROSCOPICALLY",
        "MISCONJECTURED",
        "DIOSCOREACEOUS",
        "UNDISCOVERABLY",
        "OVERDISCOUNTED",
        "DIPLEIDOSCOPES",
        "VISCOSIMETRIES",
        "MISCONJECTURES",
        "DISCOUNSELLING",
        "SPECTROSCOPIES",
        "SCINTILLASCOPE",
        "TACHISTOSCOPIC",
        "DISCOURAGINGLY",
        "DISCONFORMABLE",
        "DISCONNECTEDLY",
        "DISCOGRAPHICAL",
        "DISCONCERTEDLY",
        "LAPAROSCOPISTS",
        "METOPOSCOPICAL",
        "MEGASCOPICALLY",
        "MISCORRECTIONS",
        "REDISCOUNTABLE",
        "ANTISCORBUTICS",
        "DISCOURAGEABLE",
        "GALVANOSCOPIES",
        "UNDISCOVERABLE",
        "BRONCHOSCOPIST",
        "THERMOSCOPICAL",
        "OESOPHAGOSCOPE",
        "PERITONEOSCOPY",
        "ROENTGENOSCOPY",
        "PHONENDOSCOPES",
        "DISCONNECTIONS",
        "SIGMOIDOSCOPES",
        "STROBOSCOPICAL",
        "MISCOMPUTATION",
        "DISCOMMODITIES",
        "DEUTEROSCOPIES",
        "SIGMOIDOSCOPIC",
        "STEREOSCOPISTS",
        "DISCOMMENDABLE",
        "SCORNFULNESSES",
        "ENDOSCOPICALLY",
        "BUTTERSCOTCHES",
        "DACTYLOSCOPIES",
        "METOPOSCOPISTS",
        "CRANIOSCOPISTS",
        "DISCONTENTEDLY",
        "SYNCHRONOSCOPE",
        "MISCONNECTIONS",
        "DISCONSOLATELY",
        "MISCOMPREHENDS",
        "DISCOURAGEMENT",
        "PHARYNGOSCOPES",
        "ARCHIEPISCOPAL",
        "DISCOMMUNITIES",
        "ONEIROSCOPISTS",
        "MISCORRELATION",
        "OPHTHALMOSCOPY",
        "INDISCOVERABLE",
        "DISCOMMISSIONS",
        "SPECTROSCOPIST",
        "RONTGENOSCOPIC",
        "FLUOROSCOPISTS",
        "ESOPHAGOSCOPES",
        "DISCONTENTMENT",
        "SPINTHARISCOPE",
        "PHARYNGOSCOPIC",
        "DISCONCERTMENT",
        "CHURRIGUERESCO",
        "PREDISCOVERIES",
        "TACHISTOSCOPES",
        "MISCONSTRUCTED",
        "DISCOMBOBERATE",
        "OPHTHALMOSCOPE",
        "MISCOUNSELLING",
        "DISCOURTEOUSLY",
        "DISCOMPOSINGLY",
        "DISCONCERTIONS",
        "DISCOUNTENANCE",
        "LARYNGOSCOPIES"
    ],
    "15": [
        "DISCONFIRMATION",
        "DISCOMMISSIONED",
        "DISCOMMENDATION",
        "DISCOMBOBERATES",
        "DISCONTIGUITIES",
        "DISCOLOURATIONS",
        "OPHTHALMOSCOPIC",
        "LARYNGOSCOPISTS",
        "ROENTGENOSCOPIC",
        "DISCONTINUITIES",
        "MISCONSTRUCTION",
        "ARCHIEPISCOPACY",
        "ULTRAMICROSCOPY",
        "SIGMOIDOSCOPIES",
        "DISCOUNTENANCES",
        "SPECTROSCOPICAL",
        "SCORCHINGNESSES",
        "DISCONTENTMENTS",
        "RONTGENOSCOPIES",
        "DISCONCERTMENTS",
        "BRONCHOSCOPISTS",
        "MISCONTENTMENTS",
        "DISCOMBOBERATED",
        "ROENTGENOSCOPES",
        "MICROSCOPICALLY",
        "DISCONCERTINGLY",
        "SYNCHRONOSCOPES",
        "DISCOMMODIOUSLY",
        "BRONCHOSCOPICAL",
        "PSEUDOSCORPIONS",
        "DISCONFORMITIES",
        "VISCOSIMETRICAL",
        "COLPOSCOPICALLY",
        "RADIOSCOPICALLY",
        "SPECTROSCOPISTS",
        "ULTRAMICROSCOPE",
        "PHENAKISTOSCOPE",
        "DISCONSOLATIONS",
        "DISCOMBOBULATED",
        "MISCONSTRUCTING",
        "DISCOMBOBULATES",
        "MISCOMPREHENDED",
        "OESOPHAGOSCOPES",
        "DISCONTINUANCES",
        "PHOSPHOROSCOPES",
        "EBULLIOSCOPICAL",
        "SCINTILLOSCOPES",
        "SCOLOPENDRIFORM",
        "DISCOUNTENANCED",
        "OVERDISCOUNTING",
        "MISCONJECTURING",
        "MISCORRELATIONS",
        "VISCOELASTICITY",
        "MACROSCOPICALLY",
        "SCINTILLASCOPES",
        "SPINTHARISCOPES",
        "ANAMORPHOSCOPES",
        "MISCOMPUTATIONS",
        "OMOPLATOSCOPIES",
        "TELESTEREOSCOPE",
        "DISCOURAGEMENTS",
        "HYGROSCOPICALLY",
        "DISCONTINUATION",
        "OPHTHALMOSCOPES",
        "ARCHIEPISCOPATE",
        "DISCONTINUOUSLY",
        "PHARYNGOSCOPIES",
        "EPISCOPALIANISM"
    ]
}