{
    "4": [
        "SUPE",
        "SUPS"
    ],
    "5": [
        "SUPER",
        "SUPES",
        "SUPRA"
    ],
    "6": [
        "TOSSUP",
        "SUPPER",
        "SUPPLE",
        "CATSUP",
        "WASSUP",
        "SUPERS",
        "SUPINE",
        "SUPPED",
        "SUPLEX",
        "SUPAWN",
        "SUPPLY",
        "SUPERB"
    ],
    "7": [
        "SUPAWNS",
        "SUPPLED",
        "OVERSUP",
        "SUPERED",
        "SUPINES",
        "SUPPLER",
        "SUPPING",
        "SUPPORT",
        "SUPREME",
        "CATSUPS",
        "SUPREMO",
        "SUPPAWN",
        "SUPPLES",
        "SUPPOSE",
        "SUPPERS",
        "TOSSUPS"
    ],
    "8": [
        "SUPPEAGO",
        "SUPERSPY",
        "OVERSUPS",
        "SUPINELY",
        "SUPERPRO",
        "SUPERMEN",
        "SUPPLIED",
        "SUPERLAY",
        "SUPPLING",
        "SUPPOSAL",
        "SUPERCOW",
        "SUPPOSED",
        "SUPERHOT",
        "SUPPLIAL",
        "SUPERMOM",
        "SUPERATE",
        "SUPERJET",
        "SUPERBER",
        "SUPLEXES",
        "SUPPAWNS",
        "SUPERMAX",
        "SUPERFIT",
        "SUPPRESS",
        "SUPERTAX",
        "SUPERING",
        "SUPPOSER",
        "UNSUPPLE",
        "SUPPLELY",
        "SUPERSEX",
        "SUPPORTS",
        "SUPERLOO",
        "SUPEREGO",
        "SUPERFAN",
        "SUPREMOS",
        "SUPPOSES",
        "SUPERCAR",
        "SUPERBUG",
        "SUPPLEST",
        "SUPERIOR",
        "SUPERLIE",
        "SUPERBAD",
        "SUPREMES",
        "MARSUPIA",
        "SUPERADD",
        "SUPERCOP",
        "SUPERHIT",
        "SUPERBLY",
        "SUPERHET",
        "SUPERGUN",
        "SUPPLANT",
        "RESUPPLY",
        "SUPPLIER",
        "SUPERMAN",
        "RESUPINE",
        "SUPPERED",
        "SUPERNAL",
        "SUPREMER",
        "SUPPLIES",
        "SUPERFIX",
        "SUPINATE"
    ],
    "9": [
        "SUPERCOIL",
        "SUPERBANK",
        "SUPPLICAT",
        "SUPREMITY",
        "SUPERBITY",
        "SUPERTHIN",
        "SUPPOSING",
        "SUPERRICH",
        "SUPERGENE",
        "SUPREMACY",
        "SUPERNOVA",
        "SUPERCLUB",
        "SUPERWIDE",
        "SUPERJOCK",
        "SUPERCOPS",
        "SUPERWAVE",
        "SUPERBUGS",
        "SUPERHYPE",
        "SUPERLOAD",
        "SUPERVENE",
        "SUPERABLE",
        "SUPPLIALS",
        "SUPERMINI",
        "SUPEREGOS",
        "SUPERHETS",
        "SUPERBEST",
        "SUPERPORT",
        "MARSUPIUM",
        "SUPERSAFE",
        "SUPERATED",
        "SUPREMELY",
        "SUPERHERO",
        "SUPERETTE",
        "SUPERSOLD",
        "SUPERABLY",
        "SUPPORTED",
        "SUPERIORS",
        "SUPERCITY",
        "SUPERFLUX",
        "SUPPOSERS",
        "SUPERSIZE",
        "SUPERVISE",
        "SUPREMEST",
        "MARSUPIAL",
        "SUPERLONG",
        "SUPPLANTS",
        "SUPERBRAT",
        "SUPERLOOS",
        "SUPERMIND",
        "SUPERPOSE",
        "SUPERSALT",
        "SUPERCOOL",
        "SUPERLIES",
        "SUPERFARM",
        "MARSUPIAN",
        "SUPERWIFE",
        "SUPPLIERS",
        "SUPERREAL",
        "SUPERBOLD",
        "SUPERPROS",
        "SUPERMALE",
        "SUPERMART",
        "SUPINATES",
        "SUPERSAUR",
        "SUPERSOFT",
        "SUPERSHOW",
        "SUPERCUTE",
        "SUPERCOWS",
        "SUPERLAIN",
        "SUPPERING",
        "SUPERNATE",
        "SUPPURATE",
        "SUPERHIVE",
        "SUPERMOMS",
        "SUPERATOM",
        "SUPERROAD",
        "SUPERSELL",
        "SUPERCHIC",
        "SUPPOSALS",
        "SUPERHEAT",
        "SUPERCARS",
        "SUPERPIMP",
        "SUPERPLUS",
        "SUPINATED",
        "SUPERFAST",
        "SUPERMOTO",
        "SUPERHIGH",
        "SUPERATES",
        "SUPERBOMB",
        "SUPERSEDE",
        "SUPERJETS",
        "SUPERFUSE",
        "SUPERCOLD",
        "SUPERGLUE",
        "SUPERHITS",
        "SUPPLYING",
        "SUPINATOR",
        "SUPERGOOD",
        "SUPPORTER",
        "SUPERFIRM",
        "SUPERCEDE",
        "SUPERWEED",
        "SUPERBIKE",
        "SUPERFANS",
        "SUPERFINE",
        "SUPPLIANT",
        "SUPERFUND",
        "SUPERSALE",
        "SUPERSTUD",
        "SUPERWAIF",
        "SUPERADDS",
        "SUPERGUNS",
        "SUPERRACE",
        "SUPERSTAR"
    ],
    "10": [
        "SUPERLUNAR",
        "SUPERSAURS",
        "SUPPRESSES",
        "SUPERLYING",
        "SUPERTITLE",
        "SUPERSTOCK",
        "SUPERORDER",
        "SUPPLICATE",
        "SUPERBOARD",
        "SUPERGENES",
        "RESUPPLIES",
        "SUPERCLUBS",
        "SUPERSPEED",
        "SUPERNALLY",
        "SUPERBANKS",
        "SUPINATION",
        "SUPERHEAVY",
        "SUPERGIANT",
        "MARSUPIANS",
        "SUPPLICATS",
        "SUPERFIXES",
        "SUPERSTARS",
        "SUPERSHARP",
        "SUPERCEDED",
        "SUPERSCOUT",
        "SUPERFECTA",
        "SUPPURATES",
        "SUPERATOMS",
        "SUPERSELLS",
        "SUPERLOADS",
        "SUPPRESSED",
        "SUPPLEMENT",
        "SUPPOSEDLY",
        "SUPPLANTED",
        "SUPERPLANE",
        "MARSUPIALS",
        "SUPPRESSOR",
        "PRESUPPOSE",
        "SUPERROADS",
        "SUPERSLICK",
        "SUPPOSABLY",
        "SUPERMARTS",
        "SUPERBIKES",
        "SUPERSTORE",
        "SUPERELITE",
        "SUPERWIVES",
        "SUPPORTURE",
        "SUPEROXIDE",
        "SUPERWAVES",
        "SUPRALUNAR",
        "SUPPLEJACK",
        "SUPERBOMBS",
        "SUPPLETION",
        "SUPERBLOCK",
        "SUPERAGENT",
        "SUPERFLACK",
        "SUPERLINER",
        "SUPPLETIVE",
        "SUPERSTATE",
        "SUPINATORS",
        "SUPERTAXES",
        "RESUPPLIED",
        "SUPERHUMAN",
        "SUPERALLOY",
        "SUPERVISAL",
        "SUPPURATED",
        "SUPPERTIME",
        "SUPERSALTS",
        "SUPERETTES",
        "SUPERCOILS",
        "SUPPOSINGS",
        "SUPERSIZED",
        "SUPERVISED",
        "SUPEREXALT",
        "SUPPOSABLE",
        "SUPPORTING",
        "SUPERNOVAE",
        "SUPERVISEE",
        "SUPERSEDED",
        "SUPRAVITAL",
        "SUPERSIZES",
        "SUPERCLASS",
        "SUPRAOPTIC",
        "SUPPEAGOES",
        "SUPERWAIFS",
        "SUPERFIRMS",
        "SUPERNOVAS",
        "SUPERALTAR",
        "SUPERBITCH",
        "SUPERFLUID",
        "OVERSUPPLY",
        "SUPERWOMAN",
        "SUPERHYPES",
        "SUPPLIANTS",
        "SUPERGRASS",
        "SUPERBNESS",
        "SUPINATING",
        "SUPPORTIVE",
        "SUPERSCALE",
        "SUPERTONIC",
        "SUPERBRAIN",
        "SUPERFARMS",
        "SUPPORTERS",
        "SUPERSHOWS",
        "SUPERPIMPS",
        "SUPERIORLY",
        "SUPERTWIST",
        "SUPERCLEAN",
        "SUPERVISOR",
        "SUPERMICRO",
        "SUPERCEDES",
        "SUPERHIVES",
        "SUPERPOWER",
        "SUPERTHICK",
        "SUPERMODEL",
        "SUPERVISES",
        "SUPERSEXES",
        "SUPERFUSED",
        "SUPERGLUES",
        "UNSUPPLIED",
        "SUPERHYPED",
        "SUPERCOOLS",
        "SUPERFUNDS",
        "RESUPINATE",
        "SUPPLIABLE",
        "SUPERPORTS",
        "SUPERATING",
        "SUPERSEDER",
        "SUPERMACHO",
        "SUPERNATES",
        "SUPERCARGO",
        "SUPERVENES",
        "SUPPLIANCE",
        "SUPERSPIES",
        "SUPPLYMENT",
        "SUPERWIDES",
        "SUPERWEEDS",
        "SUPERSAVER",
        "SUPERMINIS",
        "SUPERATION",
        "SUPRARENAL",
        "MARSUPIUMS",
        "SUPERNURSE",
        "SUPERMINDS",
        "SUPPLETORY",
        "SUPERGROUP",
        "SUPPEDANEA",
        "SUPPLICANT",
        "SUPERSMART",
        "SUPERACUTE",
        "SUPERLIGHT",
        "SUPERWOMEN",
        "SUPERDENSE",
        "SUPERPOSED",
        "SUPERHEATS",
        "SUPPRESSER",
        "SUPERSTUDS",
        "SUPERMAXES",
        "SUPERBRATS",
        "SUPERSONIC",
        "SUPERJUMBO",
        "SUPERSALES",
        "SUPPLENESS",
        "SUPINENESS",
        "SUPERMALES",
        "SUPPERLESS",
        "SUPERTRUCK",
        "SUPERSWEET",
        "SUPPLANTER",
        "SUPERRACES",
        "SUPERHELIX",
        "SUPERFUSES",
        "SUPERLARGE",
        "SUPERBAZAR",
        "SUPERPOSES",
        "OVERSUPPED",
        "SUPRAPUBIC",
        "SUPERJOCKS",
        "SUPERMOTOS",
        "SUPERSEDES",
        "SUPERADDED",
        "SUPERSOUND",
        "SUPERTIGHT",
        "SUPERGLUED",
        "NONSUPPORT",
        "SUPERVENED",
        "SUPERPHYLA"
    ],
    "11": [
        "SUPERNATURE",
        "SUPERINTEND",
        "SUPERSINGER",
        "SUPERVISORS",
        "SUPPLANTERS",
        "SUPPRESSION",
        "SUPPLICATES",
        "SUPEROCTAVE",
        "SUPERVISALS",
        "SUPERIORESS",
        "SUPPOSITORY",
        "SUPEREXALTS",
        "SUPPURATION",
        "SUPRACOSTAL",
        "SUPERFLUOUS",
        "SUPREMITIES",
        "SUPERLATIVE",
        "SUPERNORMAL",
        "SUPERVISING",
        "SUPERGROWTH",
        "SUPERCOOLED",
        "SUPPLANTING",
        "SUPERPLANES",
        "SUPPURATIVE",
        "SUPPLICAVIT",
        "SUPERCARGOS",
        "SUPREMATIST",
        "SUPERORDERS",
        "SUPERHEATED",
        "SUPERSCRIPT",
        "SUPERCITIES",
        "SUPINATIONS",
        "SUPERACTIVE",
        "SUPRARENALS",
        "INSUPERABLY",
        "SUPERFICIES",
        "SUPERPLUSES",
        "OVERSUPPING",
        "SUPERSECRET",
        "SUPERSTORES",
        "SUPERTITLES",
        "SUPERPOLITE",
        "SUPERBOMBER",
        "SUPERIMPOSE",
        "SUPPLEMENTS",
        "SUPERNATANT",
        "SUPPURATING",
        "SUPERSEDEAS",
        "SUPPLICATED",
        "SUPERSELLER",
        "SUPPRESSING",
        "SUPERAGENTS",
        "SUPPOSITIVE",
        "SUPERALLOYS",
        "SUPERFLUITY",
        "SUPERDAINTY",
        "SUPPRESSANT",
        "SUPERSCREEN",
        "SUPERINDUCE",
        "SUPERFLACKS",
        "SUPERBLOCKS",
        "SUPREMACIST",
        "SUPERSOUNDS",
        "SUPPORTABLY",
        "SUPERVISION",
        "SUPEREGOIST",
        "SUPERMODERN",
        "SUPERCHURCH",
        "SUPERPOSING",
        "SUPPLYMENTS",
        "SUPPORTINGS",
        "SUPERLINERS",
        "SUPPLICANTS",
        "SUPERFECTAS",
        "SUPERHEROES",
        "SUPERVENING",
        "SUPERCHARGE",
        "SUPERSEDURE",
        "SUPERJUMBOS",
        "SUPPORTMENT",
        "INSUPERABLE",
        "SUPERFETATE",
        "SUPERVOLUTE",
        "SUPERBRIGHT",
        "UNDERSUPPLY",
        "SUPERFUSING",
        "SUPERFAMILY",
        "SUPERHYPING",
        "SUPERDELUXE",
        "SUPERAGENCY",
        "SUPERABOUND",
        "SUPERBAZAAR",
        "SUPERMODELS",
        "SUPERPROFIT",
        "SUPERNATION",
        "SUPREMACIES",
        "SUPERSEDERS",
        "SUPERSEDERE",
        "SUPERFLUIDS",
        "SUPERBAZARS",
        "SUPERPERSON",
        "SUPERSTOCKS",
        "SUPERCHERIE",
        "SUPERINFECT",
        "SUPERCOILED",
        "SUPERSEDING",
        "SUPPLETIONS",
        "SUPERPOWERS",
        "SUPERSTRING",
        "SUPERBITIES",
        "SUPPORTURES",
        "SUPERTRUCKS",
        "SUPERSCOUTS",
        "SUPERFUSION",
        "SUPERPHYLUM",
        "SUPERSTRIKE",
        "SUPERVIRILE",
        "SUPERATIONS",
        "SUPERTONICS",
        "SUPPORTLESS",
        "SUPERJACENT",
        "SUPPRESSERS",
        "SUPERSYSTEM",
        "SUPERBOARDS",
        "SUPERSTRUCT",
        "SUPERLUNARY",
        "PRESUPPOSED",
        "SUPERVISEES",
        "SUPERSCHOOL",
        "SUPERSONICS",
        "SUPERIORITY",
        "SUPPORTRESS",
        "SUPERTWISTS",
        "SUPERMICROS",
        "SUPERFLUXES",
        "SUPPLETIVES",
        "SUPERGIANTS",
        "SUPERSTRATA",
        "NONSUPPORTS",
        "SUPERSCALAR",
        "SUPERSIZING",
        "SUPERNACULA",
        "RESUPPLYING",
        "SUPERGROUPS",
        "SUPPRESSORS",
        "SUPERFEMALE",
        "SUPERLAWYER",
        "AFTERSUPPER",
        "SUPERTANKER",
        "ISOXSUPRINE",
        "SUPERMARKET",
        "SUPERSCRIBE",
        "SUPERWEAPON",
        "SUPREMENESS",
        "PRESUPPOSES",
        "SUPPEDANEUM",
        "SUPEROXIDES",
        "SUPERADDING",
        "SUPPLIANCES",
        "SUPERSAVERS",
        "SUPERFICIAL",
        "SUPPOSITION",
        "SUPERPLAYER",
        "SUPPORTABLE",
        "SUPERHEATER",
        "SUPPRESSIVE",
        "SUPERSUBTLE",
        "SUPERALTERN",
        "SUPPLEJACKS",
        "SUPERSLEUTH",
        "UNSUPPORTED",
        "SUPERSMOOTH",
        "SUPERGLUING",
        "SUPERCEDING",
        "SUPERLUXURY",
        "SUPERPRAISE",
        "SUPERSPEEDS",
        "SUPERSTATES",
        "SUPERVISORY",
        "SUPREMATISM",
        "SUPERREFINE",
        "SUPPLIANTLY",
        "SUPREMACISM",
        "SUPERFATTED",
        "SUPERHARDEN",
        "SUPERCENTER",
        "SUPERNURSES",
        "SUPERSTRONG",
        "SUPERSAFETY",
        "SUPPORTANCE",
        "SUPERBRAINS",
        "SUPPERTIMES",
        "SUPERORGASM",
        "SUPERALTARS"
    ],
    "12": [
        "SUPERCOILING",
        "SUPERGRAVITY",
        "SUPERELEVATE",
        "SUPERHELICES",
        "SUPERPROFITS",
        "SUPERINTENDS",
        "SUPERNATIONS",
        "SUPERVENIENT",
        "SUPERGROWTHS",
        "SUPERSPECIAL",
        "ISOXSUPRINES",
        "SUPERINFECTS",
        "SUPERCHERIES",
        "SUPERVENTION",
        "SUPEREGOISTS",
        "SUPERPRAISED",
        "SUPERPOWERED",
        "SUPREMACISMS",
        "SUPERFEMALES",
        "SUPERSTRINGS",
        "SUPERCHARGER",
        "SUPRAVITALLY",
        "SUPERCABINET",
        "SUPPLEMENTAL",
        "SUPERKINGDOM",
        "SUPPOSITIOUS",
        "SUPERSTRATUM",
        "SUPERSENSUAL",
        "SUPPOSITIONS",
        "SUPRACRUSTAL",
        "SUPPLEMENTED",
        "SUPERFETATES",
        "SUPERALTERNS",
        "SUPERSTRIKES",
        "SUPERPLAYERS",
        "SUPPLEMENTER",
        "SUPERCARGOES",
        "SUPERWEAPONS",
        "SUPRAORBITAL",
        "SUPERINDUCES",
        "SUPERPREMIUM",
        "SUPEREXPRESS",
        "SUPPLENESSES",
        "SUPERMARKETS",
        "SUPERSELLERS",
        "SUPREMATISTS",
        "SUPPOSITIVES",
        "SUPERSURGEON",
        "SUPEROCTAVES",
        "SUPERSTARDOM",
        "SUPERSYSTEMS",
        "OVERSUPPLIES",
        "SUPEREROGANT",
        "SUPERPATRIOT",
        "SUPEREXALTED",
        "SUPERIMPOSED",
        "SUPERGRASSES",
        "SUPPORTIVELY",
        "SUPERHEROINE",
        "SUPPLICATING",
        "SUPERTANKERS",
        "SUPERSUBTILE",
        "SUPERSCHOOLS",
        "SUPERCOOLING",
        "SUPERREFINES",
        "PRESUPPOSING",
        "SUPPORTMENTS",
        "SUPPLICATORY",
        "SUPERCILIOUS",
        "SUPERCHARGED",
        "SUPERREFINED",
        "AFTERSUPPERS",
        "SUPERABOUNDS",
        "SUPEREROGATE",
        "SUPERSEDERES",
        "SUPERBNESSES",
        "SUPERPOLYMER",
        "SUPRACILIARY",
        "SUPERQUALITY",
        "SUPPRESSANTS",
        "SUPERANNUATE",
        "SUPERFRONTAL",
        "SUPERLUMINAL",
        "SUPERFICIALS",
        "SUPERSCRIBED",
        "SUPERABILITY",
        "SUPERCLUSTER",
        "SUPERCURRENT",
        "SUPERBAZAARS",
        "OVERSUPPLIED",
        "SUPERPRAISES",
        "SUPERHIGHWAY",
        "SUPPRESSIONS",
        "SUPERNATURAL",
        "SUPERNACULUM",
        "SUPERBOMBERS",
        "UNSUPPOSABLE",
        "SUPERREALISM",
        "SUPERIMPOSES",
        "SUPERSEDURES",
        "SUPERCHARGES",
        "SUPERCENTERS",
        "SUPERSPECIES",
        "SUPERHELICAL",
        "SUPERSCRIBES",
        "SUPERSTRUCTS",
        "SUPERMASSIVE",
        "SUPERBITCHES",
        "SUPERHEAVIES",
        "SUPERCLASSES",
        "SUPERPERSONS",
        "SUPERORGASMS",
        "SUPERELASTIC",
        "SUPERSELLING",
        "SUPERCARRIER",
        "SUPERVISIONS",
        "SUPERSINGERS",
        "SUPERNATURES",
        "RESUPINATION",
        "SUPPLICATION",
        "SUPPORTANCES",
        "SUPERHEATERS",
        "SUPPRESSEDLY",
        "SUPERHELIXES",
        "SUPERORDINAL",
        "SUPERINDUCED",
        "SUPERNATANTS",
        "SUPERSEDENCE",
        "SUPREMACISTS",
        "SUPPLICAVITS",
        "SUPERHUMERAL",
        "SUPERSCREENS",
        "SUPERSECRECY",
        "UNSUPPLENESS",
        "SUPERORGANIC",
        "SUPPURATIONS",
        "SUPEROVULATE",
        "SUPINENESSES",
        "SUPERSTATION",
        "SUPERSESSION",
        "SUPERATHLETE",
        "SUPERSLEUTHS",
        "SUPERSENSORY",
        "SUPREMATISMS",
        "SUPERCONDUCT",
        "SUPRAGLOTTAL",
        "SUPERMUNDANE",
        "MARSUPIALIAN",
        "SUPEREVIDENT",
        "SUPEREMINENT",
        "SUPRAMUNDANE",
        "SUPERFETATED",
        "SUPERCILIARY",
        "SUPERREALIST",
        "SUPERHARDENS",
        "UNSUPERVISED",
        "SUPERPOSABLE",
        "SUPPURATIVES",
        "SUPERHEATING",
        "SUPERFUSIONS",
        "SUPERSTITION",
        "SUPERSEDABLE",
        "SUPERIORSHIP",
        "SUPERSCRIPTS",
        "SUPERLAWYERS",
        "SUPERTEACHER",
        "UNSUPPRESSED",
        "SUPERNACULAR",
        "SUPERPLASTIC",
        "SUPERLATIVES",
        "SUPPRESSIBLE",
        "SUPERHUMANLY",
        "SUPPLETORILY",
        "SUPRALIMINAL",
        "SUPERGLACIAL"
    ],
    "13": [
        "SUPERDOMINANT",
        "SUPERVENIENCE",
        "SUPRAMOLECULE",
        "UNDERSUPPLIES",
        "SUPERABLENESS",
        "SUPERHUMANIZE",
        "SUPERPOLYMERS",
        "SUPERINTENDED",
        "SUPERNUMERARY",
        "SUPERVIRULENT",
        "SUPERREFINING",
        "SUPPOSITIONAL",
        "UNSUPPORTEDLY",
        "SUPERLOYALIST",
        "SUPREMENESSES",
        "SUPERFLUOUSLY",
        "SUPPLICATIONS",
        "SUPERNUTRIENT",
        "SUPERCOLLIDER",
        "SUPERHIGHWAYS",
        "SUPERCAUTIOUS",
        "SUPERCRITICAL",
        "INSUPPORTABLY",
        "SUPERNATIONAL",
        "SUPERORGANISM",
        "SUPEREMINENCE",
        "SUPERMILITANT",
        "SUPERANNUATES",
        "SUPERPRAISING",
        "SUPERSTITIOUS",
        "SUPERANNUABLE",
        "SUPERNATURALS",
        "SUPERPHYSICAL",
        "SUPERMINISTER",
        "SUPRASENSIBLE",
        "SUPERABOUNDED",
        "SUPERSTRATUMS",
        "SUPERREGIONAL",
        "RESUPINATIONS",
        "SUPERCHARGING",
        "SUPERCLUSTERS",
        "SUPERPREMIUMS",
        "SUPERPOSITION",
        "SUPERHARDENED",
        "SUPERHUMERALS",
        "SUPERAGENCIES",
        "SUPERCOLUMNAR",
        "SUPERELEVATED",
        "SUPERCARRIERS",
        "SUPPOSITORIES",
        "SUPERCURRENTS",
        "SUPRACHIASMIC",
        "SUPERCOLOSSAL",
        "SUPPOSITIVELY",
        "SUPERLOBBYIST",
        "SUPERSESSIONS",
        "SUPERHEROINES",
        "SUPERCHARGERS",
        "SUPERNORMALLY",
        "SUPEREROGATED",
        "SUPRANATIONAL",
        "SUPERCOMPUTER",
        "UNSUPPORTABLE",
        "SUPERIORITIES",
        "OVERSUPPLYING",
        "SUPERSUBTLETY",
        "SUPERSEDEASES",
        "SUPERFLUIDITY",
        "SUPERIMPOSING",
        "SUPERINFECTED",
        "SUPERSTARDOMS",
        "SUPERROMANTIC",
        "SUPERGRAPHICS",
        "SUPRATEMPORAL",
        "SUPPLEMENTALS",
        "SUPERIORSHIPS",
        "SUPERKINGDOMS",
        "SUPERMAJORITY",
        "SUPERSEDENCES",
        "SUPERSALESMAN",
        "SUPERSENSIBLE",
        "SUPERELEVATES",
        "SUPERFRONTALS",
        "SUPEREXALTING",
        "SUPERIORESSES",
        "MARSUPIALIANS",
        "SUPERFLUITIES",
        "SUPERACHIEVER",
        "SUPERORDINATE",
        "SUPPLANTATION",
        "SUPERREALISTS",
        "INSUPPORTABLE",
        "SUPERTEACHERS",
        "SUPERDIPLOMAT",
        "SUPPLEMENTERS",
        "SUPERTERRIFIC",
        "SUPERACTIVITY",
        "SUPEROVULATED",
        "SUPERSCRIBING",
        "SUPERFETATION",
        "SUPPORTRESSES",
        "SUPEREROGATOR",
        "SUPERANNUATED",
        "SUPERCRIMINAL",
        "SUPERPARTICLE",
        "UNDERSUPPLIED",
        "SUPERABUNDANT",
        "SUPERINDUCING",
        "SUPERORDINARY",
        "SUPERFICIALLY",
        "SUPERSTRENGTH",
        "SUPERVIRTUOSI",
        "SUPRARATIONAL",
        "SUPERVIRTUOSO",
        "SUPERSURGEONS",
        "SUPERREALISMS",
        "SUPEREROGATES",
        "SUPERSALESMEN",
        "SUPERCABINETS",
        "SUPERPATRIOTS",
        "SUPERPOWERFUL",
        "SUPERVENTIONS",
        "SUPERLATIVELY",
        "SUPERPLASTICS",
        "SUPERNATATION",
        "SUPERADDITION",
        "UNSUPERFLUOUS",
        "SUPERCHURCHES",
        "SUPERFINENESS",
        "SUPERSTITIONS",
        "SUPERFAMILIES",
        "SUPERSYMMETRY",
        "SUPERSPECIALS",
        "SUPERSENSIBLY",
        "SUPERHUMANISE",
        "SUPERHUMANITY",
        "SUPERATHLETES",
        "SUPERCALENDER",
        "SUPERCONDUCTS",
        "SUPEROVULATES",
        "SUPERSTATIONS",
        "SUPERSATURATE",
        "SUPERFETATING",
        "SUPERMEMBRANE",
        "SUPPLEMENTARY",
        "SUPERPERSONAL",
        "SUPERTHRILLER",
        "SUPERSTRUCTED",
        "SUPERSAFETIES",
        "SUPPLEMENTING"
    ],
    "14": [
        "SUPERABSORBENT",
        "SUPERANNUATING",
        "SUPERLOBBYISTS",
        "SUPERABILITIES",
        "UNSUPPLENESSES",
        "SUPEREMINENTLY",
        "SUPERCIVILIZED",
        "SUPERANNUATION",
        "SUPERCOMPUTING",
        "SUPERHUMANIZED",
        "PRESUPPOSITION",
        "SUPEREXPRESSES",
        "SUPERADDITIONS",
        "SUPERCRIMINALS",
        "SUPERINFECTION",
        "SUPRAMOLECULES",
        "SUPERINTENDING",
        "SUPERSTRUCTION",
        "SUPRASEGMENTAL",
        "SUPERNATATIONS",
        "SUPERHUMANISES",
        "SUPERTHRILLERS",
        "SUPERFICIALISE",
        "SUPERNATURALLY",
        "SUPERSTRENGTHS",
        "SUPERVIRTUOSOS",
        "SUPERCARGOSHIP",
        "SUPERINFECTING",
        "SUPERINDUCTION",
        "INSUPPRESSIBLY",
        "SUPERCALENDERS",
        "SUPERESSENTIAL",
        "UNDERSUPPLYING",
        "SUPERFICIALITY",
        "SUPERCELESTIAL",
        "SUPERABOUNDING",
        "SUPERCILIOUSLY",
        "SUPEREMINENCES",
        "SUPERFETATIONS",
        "SUPERPHOSPHATE",
        "SUPERCILIARIES",
        "SUPERAMBITIOUS",
        "SUPERINTENDENT",
        "SUPERSTRUCTING",
        "SUPERHUMANISED",
        "SUPEREROGATIVE",
        "SUPPLANTATIONS",
        "SUPERORDINATES",
        "SUPERSENSITIVE",
        "NONSUPERVISORY",
        "SUPEROVULATING",
        "SUPERSONICALLY",
        "SUPERINSULATED",
        "SUPERSTIMULATE",
        "SUPERSCRIPTION",
        "SUPERMEMBRANES",
        "SUPPORTABILITY",
        "SUPERPHENOMENA",
        "SUPERFICIALIZE",
        "SUPERSPECTACLE",
        "SUPERIMPORTANT",
        "SUPERNUTRIENTS",
        "SUPERSYMMETRIC",
        "SUPERPOSITIONS",
        "SUPPOSITITIOUS",
        "IMMUNOSUPPRESS",
        "SUPERPATRIOTIC",
        "SUPEREROGATORS",
        "SUPERSATURATES",
        "SUPERLOYALISTS",
        "SUPERVENIENCES",
        "SUPEREXCELLENT",
        "SUPRALAPSARIAN",
        "SUPERDIPLOMATS",
        "SUPEREFFECTIVE",
        "SUPERHUMANIZES",
        "SUPPOSITIONARY",
        "SUPERORGANISMS",
        "SUPEREROGATION",
        "SUPRAMOLECULAR",
        "SUPERREGIONALS",
        "SUPERCONDUCTOR",
        "SUPEREROGATORY",
        "SUPERSTRUCTIVE",
        "SUPERSEXUALITY",
        "SUPERELEVATION",
        "SUPERINTENSITY",
        "SUPEREROGATING",
        "SUPERNUTRITION",
        "SUPRAMAXILLARY",
        "SUPERCIVILISED",
        "SUPRALIMINALLY",
        "SUPERSTRUCTURE",
        "SUPERSECRECIES",
        "SUPERCONTINENT",
        "SUPEROVULATION",
        "SUPERPARTICLES",
        "SUPERSATURATED",
        "SUPERMILITANTS",
        "SUPERNORMALITY",
        "SUPEREXPENSIVE",
        "SUPERINCUMBENT",
        "SUPERCONDUCTED",
        "SUPERTERRANEAN",
        "SUPERHARDENING",
        "SUPERORDINATED",
        "SUPERCOMPUTERS",
        "SUPERACHIEVERS",
        "SUPERGRAVITIES",
        "SUPPLICATINGLY",
        "SUPERVISORSHIP",
        "SUPERFOETATION",
        "SUPERABUNDANCE",
        "SUPERCONFIDENT",
        "SUPERLUXURIOUS",
        "SUPERIMPOSABLE",
        "SUPPOSITIOUSLY",
        "INSUPPRESSIBLE",
        "INSUPERABILITY",
        "SUPPORTIVENESS",
        "SUPPLEMENTALLY",
        "SUPERCOLLIDERS",
        "SUPERMASCULINE",
        "SUPERDOMINANTS",
        "SUPEREFFICIENT",
        "SUPERHUMANNESS",
        "SUPERELEVATING",
        "SUPERMINISTERS"
    ],
    "15": [
        "SUPEREXCELLENCE",
        "SUPERFICIALNESS",
        "SUPERNATURALISE",
        "SUPERSPECTACLES",
        "SUPEREROGATIONS",
        "SUPERNATURALISM",
        "SUPERABLENESSES",
        "SUPERELEVATIONS",
        "SUPERINCUMBENCY",
        "SUPERNATURALIZE",
        "SUPPRESSIBILITY",
        "SUPERCONVENIENT",
        "SUPERINCUMBENCE",
        "SUPERHETERODYNE",
        "SUPERABUNDANCES",
        "SUPERGOVERNMENT",
        "SUPERSTRUCTIONS",
        "SUPERCONDUCTORS",
        "SUPERORDINATING",
        "SUPERPATRIOTISM",
        "SUPERCARGOSHIPS",
        "SUPERNATURALIST",
        "SUPERPHENOMENON",
        "SUPERINTENDENTS",
        "SUPRALAPSARIANS",
        "SUPERFOETATIONS",
        "SUPERSUBTLETIES",
        "SUPERFICIALIZED",
        "SUPERNATIONALLY",
        "SUPERINFECTIONS",
        "SUPERCONDUCTING",
        "SUPERSYMMETRIES",
        "SUPPRESSIVENESS",
        "INSUPERABLENESS",
        "SUPERCONDUCTIVE",
        "SUPERCONTINENTS",
        "SUPERNUMERARIES",
        "SUPERBUREAUCRAT",
        "SUPERORDINATION",
        "SUPEREXALTATION",
        "SUPERSPECIALIST",
        "SUPERPLASTICITY",
        "SUPERFLUOUSNESS",
        "SUPERINDUCEMENT",
        "SUPERVISORSHIPS",
        "SUPERORGANICISM",
        "SUPERCONDUCTION",
        "SUPERFLUIDITIES",
        "SUPERSTITIOUSLY",
        "SUPERCONFIDENCE",
        "SUPERINDUCTIONS",
        "SUPERFICIALISED",
        "SUPERSATURATING",
        "SUPERHUMANIZING",
        "SUPERMAJORITIES",
        "SUPERINTENDENCY",
        "SUPPLEMENTARILY",
        "SUPERSATURATION",
        "SUPERSTIMULATES",
        "SUPERSTIMULATED",
        "SUPERABUNDANTLY",
        "SUPERSTRUCTURES",
        "SUPERPARASITISM",
        "SUPERHUMANITIES",
        "SUPPLEMENTARIES",
        "SUPPOSITIONALLY",
        "SUPERNUTRITIONS",
        "SUPERFICIALIZES",
        "SUPERCOMPUTINGS",
        "SUPERACTIVITIES",
        "SUPERFINENESSES",
        "SUPERCALENDERED",
        "SUPERSTRUCTURAL",
        "SUPERINTENDENCE",
        "SUPERFICIALISES",
        "PRESUPPOSITIONS",
        "SUPERABSORBENTS",
        "SUPERLATIVENESS",
        "SUPPLEMENTATION",
        "SUPPORTABLENESS",
        "SUPPOSITIONLESS",
        "SUPERINDIVIDUAL",
        "SUPERSCRIPTIONS",
        "SUPEROVULATIONS",
        "SUPERORGANICIST",
        "SUPERIMPOSITION",
        "SUPERHUMANISING",
        "SUPERADDITIONAL",
        "SUPERANNUATIONS",
        "SUPRANATIONALLY",
        "SUPERPHOSPHATES",
        "SUPEREFFICIENCY"
    ]
}