{
    "4": [
        "QUAI"
    ],
    "5": [
        "QUAIL",
        "QUAIR",
        "QUAIS"
    ],
    "6": [
        "GUAIAC",
        "QUAICH",
        "QUAIGH",
        "QUAINT",
        "QUAILS",
        "SQUAIL",
        "QUAIRS"
    ],
    "7": [
        "GUAIACS",
        "QUAIGHS",
        "QUAICHS",
        "SQUAILS",
        "QUAILED"
    ],
    "8": [
        "GUAIOCUM",
        "SQUAILED",
        "CINQUAIN",
        "QUAILING",
        "GUAIACUM",
        "GUAIACOL",
        "QUAINTLY",
        "ACQUAINT",
        "QUAINTER",
        "SQUAILER",
        "QUAICHES"
    ],
    "9": [
        "GUAIACUMS",
        "CINQUAINS",
        "SQUAILERS",
        "QUAILINGS",
        "TINGUAITE",
        "QUAINTEST",
        "GUAIACOLS",
        "ACQUAINTS",
        "GUAIOCUMS",
        "SQUAILING"
    ],
    "10": [
        "REACQUAINT",
        "RELIQUAIRE",
        "UNACQUAINT",
        "QUAINTNESS",
        "ACQUAINTED",
        "TINGUAITES",
        "SQUAILINGS"
    ],
    "11": [
        "REACQUAINTS",
        "PREACQUAINT",
        "RELIQUAIRES",
        "ACQUAINTING"
    ],
    "12": [
        "QUAINTNESSES",
        "REACQUAINTED",
        "PREACQUAINTS",
        "ACQUAINTANCE",
        "UNACQUAINTED"
    ],
    "13": [
        "ACQUAINTANCES",
        "PREACQUAINTED",
        "REACQUAINTING"
    ],
    "14": [
        "UNACQUAINTANCE",
        "REACQUAINTANCE",
        "PREACQUAINTING"
    ],
    "15": [
        "REACQUAINTANCES",
        "PREACQUAINTANCE",
        "UNACQUAINTANCES"
    ]
}